[{"id": 1, "number": "115", "street": "Zilverschoonstraat", "type": "Restafval", "subtype": "60L", "condition": "Redelijk", "color": "Antraciet", "supplier": "Vconsyst", "lat": 52.98493810614154, "lng": 6.579688010432916}, {"id": 2, "number": "138", "street": "Oosterpark", "type": "Restafval", "subtype": "60L", "condition": "Redelijk", "color": "Antraciet", "supplier": "Vconsyst", "lat": 52.99308290171354, "lng": 6.5739335419617175}, {"id": 3, "number": "116", "street": "Zilverschoonstraat", "type": "Restafval", "subtype": "60L", "condition": "Redelijk", "color": "Antraciet", "supplier": "Vconsyst", "lat": 52.98526758309428, "lng": 6.578816488300459}, {"id": 4, "number": "134", "street": "Gerard Doustraat", "type": "Restafval", "subtype": "60L", "condition": "Redelijk", "color": "Antraciet", "supplier": "Vconsyst", "lat": 52.99449575158154, "lng": 6.5806977356768925}, {"id": 5, "number": "139", "street": "Oosterpark", "type": "Restafval", "subtype": "60L", "condition": "Redelijk", "color": "Antraciet", "supplier": "Vconsyst", "lat": 52.992541404268074, "lng": 6.575420961629383}, {"id": 6, "number": "250", "street": "Tuinstraat", "type": "Restafval", "subtype": "60L", "condition": "Goed", "color": "Antraciet", "supplier": "Vconsyst", "lat": 52.9895797785755, "lng": 6.5772329668637095}, {"id": 7, "number": "132", "street": "Oosterparrallelstraat", "type": "Restafval", "subtype": "60L", "condition": "Redelijk", "color": "Antraciet", "supplier": "Vconsyst", "lat": 52.99118922475143, "lng": 6.571486909318501}, {"id": 8, "number": "122", "street": "Dotterbloemstraat", "type": "Restafval", "subtype": "60L", "condition": "Slecht", "color": "Antraciet", "supplier": "Vconsyst", "lat": 52.987590392090716, "lng": 6.579988509471873}, {"id": 9, "number": "121", "street": "Dotterbloemstraat", "type": "Restafval", "subtype": "60L", "condition": "Redelijk", "color": "Antraciet", "supplier": "Vconsyst", "lat": 52.98730922981162, "lng": 6.580486581279453}, {"id": 10, "number": "141", "street": "Steenwijk", "type": "Restafval", "subtype": "60L", "condition": "Redelijk", "color": "Antraciet", "supplier": "Vconsyst", "lat": 52.994692010266256, "lng": 6.575185126019522}, {"id": 11, "number": "133", "street": "Gerard Doustraat", "type": "Restafval", "subtype": "60L", "condition": "Slecht", "color": "Antraciet", "supplier": "Vconsyst", "lat": 52.99447672366579, "lng": 6.579894764882071}, {"id": 12, "number": "136", "street": "Oosterpark", "type": "Restafval", "subtype": "60L", "condition": "Redelijk", "color": "Antraciet", "supplier": "Vconsyst", "lat": 52.993084573577235, "lng": 6.575687524113524}, {"id": 13, "number": "128", "street": "Anreperstraat", "type": "Restafval", "subtype": "60L", "condition": "Redelijk", "color": "Antraciet", "supplier": "Vconsyst", "lat": 52.98611223348532, "lng": 6.570774566857784}, {"id": 14, "number": "135", "street": "Mezenlaan", "type": "Restafval", "subtype": "60L", "condition": "Redelijk", "color": "Antraciet", "supplier": "Vconsyst", "lat": 52.99265000634186, "lng": 6.577020845879027}, {"id": 15, "number": "120", "street": "Dotterbloemstraat", "type": "Restafval", "subtype": "60L", "condition": "Redelijk", "color": "Antraciet", "supplier": "Vconsyst", "lat": 52.98695871251229, "lng": 6.580804661246839}, {"id": 16, "number": "137", "street": "Oosterpark", "type": "Restafval", "subtype": "60L", "condition": "Redelijk", "color": "Antraciet", "supplier": "Vconsyst", "lat": 52.993539851763046, "lng": 6.574323223945448}, {"id": 17, "number": null, "street": null, "type": null, "subtype": null, "condition": null, "color": null, "supplier": null, "lat": 52.989749159560496, "lng": 6.5823149439367965}, {"id": 18, "number": "321", "street": "Vredeveldseweg ", "type": "Restafval", "subtype": "60L", "condition": "Redelijk", "color": "Antraciet", "supplier": "Vconsyst", "lat": 52.988156147738906, "lng": 6.584938445876297}, {"id": 19, "number": "114", "street": "Speenkruidstraat", "type": "Restafval", "subtype": "60L", "condition": "Redelijk", "color": "Antraciet", "supplier": "Vconsyst", "lat": 52.9845818548345, "lng": 6.580134198244639}, {"id": 20, "number": "113", "street": "Speenkruidstraat", "type": "Restafval", "subtype": "60L", "condition": "Redelijk", "color": "Antraciet", "supplier": "Vconsyst", "lat": 52.985226722081414, "lng": 6.581132419663085}, {"id": 21, "number": "114", "street": "Speenkruidstraat", "type": "Papier", "subtype": "Klep", "condition": "Goed", "color": "Antraciet", "supplier": "Vconsyst", "lat": 52.98455897899324, "lng": 6.580180494719451}, {"id": 22, "number": "714", "street": "Speenkruidstraat", "type": "PMD", "subtype": "60L", "condition": "Goed", "color": "Antraciet", "supplier": "de Rooij", "lat": 52.984570619990635, "lng": 6.580157686494379}, {"id": 23, "number": "118", "street": "Zilverschoonstraat", "type": "Restafval", "subtype": "60L", "condition": "Redelijk", "color": "Antraciet", "supplier": "Vconsyst", "lat": 52.98582296585242, "lng": 6.5778235840102}, {"id": 24, "number": "252", "street": "Resedastraat", "type": "Restafval", "subtype": "60L", "condition": "Slecht", "color": "Antraciet", "supplier": "Vconsyst", "lat": 52.98996903902606, "lng": 6.57443902936197}, {"id": 25, "number": "131", "street": "Lod. Napoleonplein", "type": "Restafval", "subtype": "60L", "condition": "Redelijk", "color": "Antraciet", "supplier": "Vconsyst", "lat": 52.98824347734425, "lng": 6.572073570284472}, {"id": 26, "number": "253", "street": "Pelikaanstraat", "type": "Restafval", "subtype": "60L", "condition": "Slecht", "color": "Antraciet", "supplier": "Vconsyst", "lat": 52.98872612526723, "lng": 6.574441281438394}, {"id": 27, "number": "127", "street": "Berkenstraat", "type": "Restafval", "subtype": "60L", "condition": "Redelijk", "color": "Antraciet", "supplier": "Vconsyst", "lat": 52.985205460343344, "lng": 6.569777330891187}, {"id": 28, "number": "117", "street": "Zilverschoonstraat", "type": "Restafval", "subtype": "60L", "condition": "Redelijk", "color": "Antraciet", "supplier": "Vconsyst", "lat": 52.98554560579505, "lng": 6.578319816966387}, {"id": 29, "number": "123", "street": "Dotterbloemstraat", "type": "Restafval", "subtype": "60L", "condition": "Redelijk", "color": "Antraciet", "supplier": "Vconsyst", "lat": 52.987877528605054, "lng": 6.5791993691391655}, {"id": 30, "number": "251", "street": "Lindelaan", "type": "Restafval", "subtype": "60L", "condition": "Redelijk", "color": "Antraciet", "supplier": "Vconsyst", "lat": 52.985322846746975, "lng": 6.571417763296152}, {"id": 31, "number": "271", "street": "Herman Broodstraat", "type": "Restafval", "subtype": "60L", "condition": "Goed", "color": "Antraciet", "supplier": "Vconsyst", "lat": 52.99743415276758, "lng": 6.574330954846769}, {"id": 32, "number": null, "street": null, "type": null, "subtype": null, "condition": null, "color": null, "supplier": null, "lat": 53.00193760870428, "lng": 6.567502383366773}, {"id": 33, "number": "270", "street": "Huygensstraat", "type": "Restafval", "subtype": "60L", "condition": "Redelijk", "color": "Antraciet", "supplier": "Vconsyst", "lat": 53.00067869725861, "lng": 6.566888171071053}, {"id": 34, "number": "267", "street": "Vondellaan ", "type": "Papier", "subtype": "Klep", "condition": "Goed", "color": "Antraciet", "supplier": "Wastevision", "lat": 53.001805808107974, "lng": 6.568915951636623}, {"id": 35, "number": "269", "street": "Huygensstaat", "type": "Restafval", "subtype": "60L", "condition": "Slecht", "color": "Antraciet", "supplier": "Vconsyst", "lat": 53.00159584782307, "lng": 6.566747858715251}, {"id": 36, "number": "159", "street": "Kuyperstraat", "type": "Restafval", "subtype": "60L", "condition": "Goed", "color": "Antraciet", "supplier": "Vconsyst", "lat": 53.001792334806254, "lng": 6.561934423114878}, {"id": 37, "number": "280", "street": "Thorbeckelaan", "type": "Papier", "subtype": "Klep", "condition": "Goed", "color": "Antraciet", "supplier": "Vconsyst", "lat": 52.99976814659356, "lng": 6.551948524939454}, {"id": 38, "number": "280", "street": "Thorbeckelaan", "type": "Restafval", "subtype": "100L", "condition": "Redelijk", "color": "Blauw", "supplier": "Vconsyst", "lat": 52.99975393146225, "lng": 6.551962132619387}, {"id": 39, "number": "268", "street": "Vondellaan ", "type": "Papier", "subtype": "60L", "condition": "Redelijk", "color": "Antraciet", "supplier": "Wastevision", "lat": 53.000995101740735, "lng": 6.569069359632613}, {"id": 40, "number": "168", "street": "Nansenstraat", "type": "Papier", "subtype": "Klep", "condition": "Goed", "color": "Antraciet", "supplier": "Vconsyst", "lat": 52.99842896974313, "lng": 6.5544566616369115}, {"id": 41, "number": "165", "street": "Schaepmanstraat", "type": "Restafval", "subtype": "60L", "condition": "Redelijk", "color": "Antraciet", "supplier": "Vconsyst", "lat": 52.99911195397523, "lng": 6.558167706280186}, {"id": 42, "number": "168", "street": "Nansenstraat", "type": "Restafval", "subtype": "100L", "condition": "Redelijk", "color": "Antraciet", "supplier": "Vconsyst", "lat": 52.99841641501535, "lng": 6.554476925833069}, {"id": 43, "number": "278", "street": "Anne de Vriesestraat", "type": "Restafval", "subtype": "60L", "condition": "Redelijk", "color": "Antraciet", "supplier": "Vconsyst", "lat": 53.00006672273825, "lng": 6.5670671280520585}, {"id": 44, "number": "265", "street": "Paganinilaan", "type": "Restafval", "subtype": "60L", "condition": "Goed", "color": "Antraciet", "supplier": "Vconsyst", "lat": 53.01011990372502, "lng": 6.564069981751607}, {"id": 45, "number": "275", "street": "van Houtenstraat", "type": "Restafval", "subtype": "60L", "condition": "Goed", "color": "Antraciet", "supplier": "Vconsyst", "lat": 52.99982872655008, "lng": 6.563491394843412}, {"id": 46, "number": "119", "street": "Breestraat", "type": "Restafval", "subtype": "60L", "condition": "Goed", "color": "Antraciet", "supplier": "Vconsyst", "lat": 52.98651073535633, "lng": 6.582597710232051}, {"id": 47, "number": "130", "street": "Anemoonstraat", "type": "Restafval", "subtype": "60L", "condition": "Goed", "color": "Antraciet", "supplier": "Vconsyst", "lat": 52.987642433542156, "lng": 6.570535739858024}, {"id": 48, "number": "129", "street": "Anemoonstraat", "type": "Restafval", "subtype": "60L", "condition": "Goed", "color": "Antraciet", "supplier": "Vconsyst", "lat": 52.98700112717711, "lng": 6.57032048824459}, {"id": 49, "number": "126", "street": "Sleutelbloemstraat", "type": "Restafval", "subtype": "60L", "condition": "Redelijk", "color": "Antraciet", "supplier": "Vconsyst", "lat": 52.98780835469287, "lng": 6.581844147676186}, {"id": 50, "number": "112", "street": "Speenkruidstraat", "type": "Restafval", "subtype": "60L", "condition": "Redelijk", "color": "Antraciet", "supplier": "Vconsyst", "lat": 52.98587076309913, "lng": 6.582123425813177}, {"id": 51, "number": "112", "street": "Speenkruidstraat", "type": "Papier", "subtype": "Klep", "condition": "Redelijk", "color": "Antraciet", "supplier": "Vconsyst", "lat": 52.98584733686842, "lng": 6.582170734689283}, {"id": 52, "number": "712", "street": "Speenkruidstraat", "type": "PMD", "subtype": "60L", "condition": "Goed", "color": "Antraciet", "supplier": "de Rooij", "lat": 52.985858977518596, "lng": 6.582147153014779}, {"id": 53, "number": "146", "street": "Oldengaardestraat", "type": "Restafval", "subtype": "60L", "condition": "Redelijk", "color": "Antraciet", "supplier": "Vconsyst", "lat": 53.005939788051045, "lng": 6.554444159783108}, {"id": 54, "number": "292", "street": "Obrechtlaan", "type": "Restafval", "subtype": "60L", "condition": "Goed", "color": "Antraciet", "supplier": "Vconsyst", "lat": 53.00795147331692, "lng": 6.559508636776138}, {"id": 55, "number": "167", "street": "Troelstralaan", "type": "Restafval", "subtype": "60L", "condition": "Goed", "color": "Antraciet", "supplier": "Vconsyst", "lat": 52.99872644684568, "lng": 6.5542395738670445}, {"id": 56, "number": "160", "street": "Kuyperstraat", "type": "Restafval", "subtype": "60L", "condition": "Goed", "color": "Antraciet", "supplier": "Vconsyst", "lat": 53.00168628031916, "lng": 6.56115658628338}, {"id": 57, "number": null, "street": null, "type": null, "subtype": null, "condition": null, "color": null, "supplier": null, "lat": 53.001894329157714, "lng": 6.555690835446205}, {"id": 58, "number": "147", "street": "Oosterbroekstraat", "type": "Restafval", "subtype": "60L", "condition": "Redelijk", "color": "Antraciet", "supplier": "Vconsyst", "lat": 53.00573355116471, "lng": 6.555990146912333}, {"id": 59, "number": "239", "street": "Mensingestraat", "type": "Restafval", "subtype": "60L", "condition": "Goed", "color": "Antraciet", "supplier": "Vconsyst", "lat": 53.00653265293512, "lng": 6.556816520616937}, {"id": 60, "number": "145", "street": "Oldengaardestraat", "type": "Restafval", "subtype": "60L", "condition": "Redelijk", "color": "Antraciet", "supplier": "Vconsyst", "lat": 53.006282046977056, "lng": 6.553053355720868}, {"id": 61, "number": "258", "street": "Perzikstraat", "type": "Restafval", "subtype": "60L", "condition": "Redelijk", "color": "Antraciet", "supplier": null, "lat": 53.00380303436687, "lng": 6.517024906691682}, {"id": 62, "number": "261", "street": "Stedewaarts", "type": "Restafval", "subtype": "60L", "condition": "Redelijk", "color": "Antraciet", "supplier": null, "lat": 53.00468507022227, "lng": 6.507949781636758}, {"id": 63, "number": "259", "street": "Perzikstraat", "type": "Restafval", "subtype": "60L", "condition": "Redelijk", "color": "Antraciet", "supplier": null, "lat": 53.004587388042125, "lng": 6.515433170161643}, {"id": 64, "number": "110", "street": "Planetenlaan", "type": "Restafval", "subtype": "60L", "condition": "Redelijk", "color": "Antraciet", "supplier": "Vconsyst", "lat": 52.9935148708511, "lng": 6.512765091122808}, {"id": 65, "number": "244", "street": "Tjalk", "type": "Restafval", "subtype": "60L", "condition": "Redelijk", "color": "Antraciet", "supplier": "Vconsyst", "lat": 52.99659311913245, "lng": 6.512083948948512}, {"id": 66, "number": "901", "street": "Kleuvenstee", "type": "Glas", "subtype": "Wit", "condition": "Slecht", "color": "Antraciet", "supplier": "Vconsyst", "lat": 53.01808803283482, "lng": 6.586332110174395}, {"id": 67, "number": "249", "street": "M.L. Kingweg", "type": "Restafval", "subtype": "100L", "condition": "Redelijk", "color": "Blauw", "supplier": "Vconsyst", "lat": 53.014994087550974, "lng": 6.580169749970334}, {"id": 68, "number": "102", "street": "Beunheugte", "type": "Restafval", "subtype": "60L", "condition": "Redelijk", "color": "Antraciet", "supplier": "Vconsyst", "lat": 53.01738795327481, "lng": 6.583283044843764}, {"id": 69, "number": "104", "street": "Schepelgoorn", "type": "Restafval", "subtype": "60L", "condition": "Redelijk", "color": "Antraciet", "supplier": "Vconsyst", "lat": 53.016600220088144, "lng": 6.58498431744798}, {"id": 70, "number": "247", "street": "Kleuvenstee noord", "type": "Restafval", "subtype": "100L", "condition": "Slecht", "color": "Antraciet", "supplier": "Vconsyst", "lat": 53.01703518126423, "lng": 6.585974491758096}, {"id": 71, "number": "296", "street": "Zuiderkade", "type": "Papier", "subtype": "60L", "condition": "Redelijk", "color": "Antraciet", "supplier": "Vconsyst", "lat": 52.99917903700886, "lng": 6.513487621377206}, {"id": 72, "number": "919", "street": "Zuiderpoort", "type": "Glas", "subtype": "Wit", "condition": "Slecht", "color": "Antraciet", "supplier": "Vconsyst", "lat": 52.99950337265071, "lng": 6.513180688604171}, {"id": 73, "number": "919", "street": "Zuiderpoort", "type": "Glas", "subtype": "Bruin/Groen", "condition": "Slecht", "color": "Antraciet", "supplier": "Vconsyst", "lat": 52.99949708679343, "lng": 6.513202110728755}, {"id": 74, "number": "296", "street": "Zuiderkade", "type": "Restafval", "subtype": "100L", "condition": "Redelijk", "color": "Antraciet", "supplier": "Vconsyst", "lat": 52.999163301972374, "lng": 6.51347893197345}, {"id": 75, "number": "294", "street": "Gildestraat", "type": "Papier", "subtype": "Klep", "condition": "Redelijk", "color": "Antraciet", "supplier": "Vconsyst", "lat": 53.00028186631842, "lng": 6.512041437076007}, {"id": 76, "number": "245", "street": "Aardbeihof", "type": "Restafval", "subtype": "60L", "condition": "Redelijk", "color": "Antraciet", "supplier": null, "lat": 53.003367144086084, "lng": 6.513784145371009}, {"id": 77, "number": "288", "street": "Bosroos", "type": "Restafval", "subtype": "100L", "condition": "Goed", "color": "Antraciet", "supplier": "Wastevision", "lat": 53.008391373329545, "lng": 6.513377958640571}, {"id": 78, "number": "246", "street": "Frambozenrode", "type": "Restafval", "subtype": "60L", "condition": "Redelijk", "color": "Antraciet", "supplier": null, "lat": 53.003288091045455, "lng": 6.515408369473309}, {"id": 79, "number": "289", "street": "Schoolstraat", "type": "Restafval", "subtype": "100L", "condition": "Redelijk", "color": "Antraciet", "supplier": null, "lat": 53.001230916108156, "lng": 6.514004513788308}, {"id": 80, "number": "294", "street": "Gildestraat", "type": "Restafval", "subtype": "100L", "condition": "Redelijk", "color": "Antraciet", "supplier": null, "lat": 53.00029913467456, "lng": 6.512041883538731}, {"id": 81, "number": "293", "street": "Schoolstraat", "type": "Restafval", "subtype": "100L", "condition": "Redelijk", "color": "Antraciet", "supplier": null, "lat": 53.00103632085556, "lng": 6.515116049594991}, {"id": 82, "number": "293", "street": "Schoolstraat", "type": "Papier", "subtype": "60L", "condition": "Redelijk", "color": "Antraciet", "supplier": null, "lat": 53.00102614393403, "lng": 6.515140291531263}, {"id": 83, "number": "103", "street": "Kleuvenstee", "type": "Restafval", "subtype": "100L", "condition": "Goed", "color": "Antraciet", "supplier": "Vconsyst", "lat": 53.01737279013562, "lng": 6.5844696474688655}, {"id": 84, "number": "109", "street": "Amstelstraat", "type": "Papier", "subtype": "Klep", "condition": "Goed", "color": "Antraciet", "supplier": "Vconsyst", "lat": 53.00814348507535, "lng": 6.541856115317446}, {"id": 85, "number": "109R", "street": "Amstelstraat", "type": "Restafval", "subtype": "60L", "condition": "Goed", "color": "Antraciet", "supplier": "Vconsyst", "lat": 53.008006331744426, "lng": 6.541618210887473}, {"id": 86, "number": "109L", "street": "Amstelstraat", "type": "Restafval", "subtype": "60L", "condition": "Goed", "color": "Antraciet", "supplier": "Vconsyst", "lat": 53.00805479576562, "lng": 6.541541200114801}, {"id": 87, "number": null, "street": "Maasstraat", "type": "Glas", "subtype": "Wit", "condition": "Goed", "color": "Antraciet", "supplier": "Vconsyst", "lat": 53.006518064897676, "lng": 6.539980834551134}, {"id": 88, "number": "924", "street": "Het sticht", "type": "Glas", "subtype": "Bruin/Groen", "condition": "Redelijk", "color": "Antraciet", "supplier": null, "lat": 52.98372085787949, "lng": 6.535296470687418}, {"id": 89, "number": "111", "street": "Het sticht", "type": "Restafval", "subtype": "100L", "condition": "Redelijk", "color": "Antraciet", "supplier": null, "lat": 52.984012352623395, "lng": 6.534471784917228}, {"id": 90, "number": null, "street": "Maasstraat", "type": "Glas", "subtype": "Bruin/Groen", "condition": "Redelijk", "color": "Antraciet", "supplier": "Vconsyst", "lat": 53.00651338762198, "lng": 6.5400092267039955}, {"id": 91, "number": "262", "street": "Rijnstraat", "type": "Restafval", "subtype": "60L", "condition": "Goed", "color": "Antraciet", "supplier": "Vconsyst", "lat": 53.01036247950386, "lng": 6.545472424529154}, {"id": 92, "number": "291", "street": "Vredeveldseweg", "type": "Restafval", "subtype": "Trommel", "condition": "Slecht", "color": "Antraciet", "supplier": null, "lat": 52.9888492249592, "lng": 6.581495465700346}, {"id": 93, "number": "113", "street": "Speenkruidstraat", "type": "Papier", "subtype": "Klep", "condition": "Redelijk", "color": "Antraciet", "supplier": "Vconsyst", "lat": 52.985202312318144, "lng": 6.581177482751015}, {"id": 94, "number": "714", "street": "Speenkruidstraat", "type": "PMD", "subtype": "60L", "condition": "Goed", "color": "Antraciet", "supplier": "de Rooij", "lat": 52.98521504340449, "lng": 6.58115443737071}, {"id": 95, "number": "291pap", "street": "Vredeveldseweg", "type": "Papier", "subtype": "Klep", "condition": "Redelijk", "color": "Antraciet", "supplier": null, "lat": 52.98883652360412, "lng": 6.581514642036718}, {"id": 96, "number": "299", "street": "Bremstraat", "type": "Restafval", "subtype": "60L", "condition": "Goed", "color": "Antraciet", "supplier": null, "lat": 52.98909218199805, "lng": 6.579268069597155}, {"id": 97, "number": "297", "street": "Middenweg", "type": "Restafval", "subtype": "100L", "condition": "Goed", "color": "Antraciet", "supplier": "Vconsyst", "lat": 52.976553426788364, "lng": 6.569945885381204}, {"id": 98, "number": "298", "street": "Middenweg", "type": "Restafval", "subtype": "100L", "condition": "Goed", "color": "Antraciet", "supplier": "Vconsyst", "lat": 52.97610571279902, "lng": 6.5682124656662575}, {"id": 99, "number": "257", "street": "Stoepveldsingel", "type": "Restafval", "subtype": "60L", "condition": "Redelijk", "color": "Antraciet", "supplier": "Vconsyst", "lat": 53.01245703069284, "lng": 6.590145619353896}, {"id": 100, "number": "255", "street": "Overstoep", "type": "Restafval", "subtype": "60L", "condition": "Goed", "color": "Antraciet", "supplier": "Vconsyst", "lat": 53.01314712590304, "lng": 6.588728665333784}, {"id": 101, "number": null, "street": null, "type": null, "subtype": null, "condition": null, "color": null, "supplier": null, "lat": 53.01607440867927, "lng": 6.561988766697987}, {"id": 102, "number": "100", "street": "Steigermesschen", "type": "Restafval", "subtype": "60L", "condition": "Goed", "color": "Antraciet", "supplier": "Vconsyst", "lat": 53.02559325450516, "lng": 6.591103137208526}, {"id": 103, "number": "248", "street": "Kleuvenstee zuid", "type": "Restafval", "subtype": "100L", "condition": "Slecht", "color": "Antraciet", "supplier": "Vconsyst", "lat": 53.01810566315666, "lng": 6.585407878494314}, {"id": 104, "number": "902", "street": "Kleuvenstee", "type": "Glas", "subtype": "Bruin/Groen", "condition": "Slecht", "color": "Antraciet", "supplier": "Vconsyst", "lat": 53.01807262784546, "lng": 6.586346573050465}, {"id": 105, "number": "101", "street": "Fuutmesschen", "type": "Restafval", "subtype": "60L", "condition": "Goed", "color": "Antraciet", "supplier": "Vconsyst", "lat": 53.02454651870921, "lng": 6.596059499262187}, {"id": 106, "number": null, "street": null, "type": null, "subtype": null, "condition": null, "color": null, "supplier": null, "lat": 53.016040364472296, "lng": 6.561092073771261}, {"id": 107, "number": "290", "street": "Witterhoofdweg", "type": "Restafval", "subtype": "100L", "condition": "Redelijk", "color": "Antraciet", "supplier": null, "lat": 52.9874585130884, "lng": 6.528739573105516}, {"id": 108, "number": "290", "street": "Witterhoofdweg", "type": "Papier", "subtype": "60L", "condition": "Redelijk", "color": "Antraciet", "supplier": null, "lat": 52.98744957296776, "lng": 6.528715882734828}, {"id": 109, "number": "923", "street": "Het sticht", "type": "Glas", "subtype": "Wit", "condition": "Slecht", "color": "Antraciet", "supplier": null, "lat": 52.98370913823375, "lng": 6.5353152670364185}, {"id": 110, "number": "108", "street": "Gravenlanden", "type": "Restafval", "subtype": "60L", "condition": "Redelijk", "color": "Antraciet", "supplier": "Vconsyst", "lat": 53.01858434485292, "lng": 6.56157588392542}, {"id": 111, "number": null, "street": null, "type": null, "subtype": null, "condition": null, "color": null, "supplier": null, "lat": 53.016038024999375, "lng": 6.561061192386742}, {"id": 112, "number": "106", "street": "Walakker", "type": "Restafval", "subtype": "60L", "condition": "Redelijk", "color": "Antraciet", "supplier": "Vconsyst", "lat": 53.016342259711784, "lng": 6.5594037836195636}, {"id": 113, "number": "107", "street": "Scharmbarg", "type": "Restafval", "subtype": "60L", "condition": "Redelijk", "color": "Antraciet", "supplier": "Vconsyst", "lat": 53.01671101678446, "lng": 6.560131053385345}, {"id": 114, "number": "157", "street": "S. Lohmanstraat", "type": "Restafval", "subtype": "60L", "condition": "Redelijk", "color": "Antraciet", "supplier": "Vconsyst", "lat": 53.000745288065055, "lng": 6.557710366782496}, {"id": 115, "number": "210", "street": "Vaart nu", "type": "Restafval", "subtype": "60L", "condition": "Goed", "color": "Antraciet", "supplier": "Vconsyst", "lat": 52.99403632120867, "lng": 6.553210643540589}, {"id": 116, "number": "286", "street": "Vaart zz", "type": "Restafval", "subtype": "60L", "condition": "Redelijk", "color": "Antraciet", "supplier": "Vconsyst", "lat": 52.993718269048756, "lng": 6.5549390228084885}, {"id": 117, "number": "285", "street": "Vaart ze", "type": "Restafval", "subtype": "60L", "condition": "Redelijk", "color": "Antraciet", "supplier": "Vconsyst", "lat": 52.99365317433294, "lng": 6.556963308927615}, {"id": 118, "number": "211", "street": "Weierstraat", "type": "Restafval", "subtype": "100L", "condition": "Redelijk", "color": "Blauw", "supplier": "Vconsyst", "lat": 52.99480347796771, "lng": 6.55931373559715}, {"id": 119, "number": "203", "street": "Beilerstraat", "type": "Restafval", "subtype": "60L", "condition": "Goed", "color": "Antraciet", "supplier": "Vconsyst", "lat": 52.988688658099015, "lng": 6.559141925612552}, {"id": 120, "number": null, "street": "Nijlandstraat", "type": "Glas", "subtype": "Wit", "condition": "Redelijk", "color": "Antraciet", "supplier": "Vconsyst", "lat": 52.99821573404641, "lng": 6.569957271527447}, {"id": 121, "number": null, "street": "Nijlandstraat", "type": "Glas", "subtype": "Bruin/Groen", "condition": "Redelijk", "color": "Antraciet", "supplier": "Vconsyst", "lat": 52.99821542588052, "lng": 6.569927530105011}, {"id": 122, "number": "205", "street": "Oosterhoutstraat", "type": "Restafval", "subtype": "60L", "condition": "Redelijk", "color": "Antraciet", "supplier": "Vconsyst", "lat": 52.99151943050745, "lng": 6.563793744411824}, {"id": 123, "number": "204", "street": "Beatrixstraat", "type": "Restafval", "subtype": "60L", "condition": "Goed", "color": "Antraciet", "supplier": "Vconsyst", "lat": 52.99115919692535, "lng": 6.562551101286061}, {"id": 124, "number": "234", "street": "Oranjestraat", "type": "Restafval", "subtype": "60L", "condition": "Redelijk", "color": "Antraciet", "supplier": "Vconsyst", "lat": 52.994220655939614, "lng": 6.568436249478256}, {"id": 125, "number": "234A", "street": "Oranjestraat", "type": "Restafval", "subtype": "60L", "condition": "Redelijk", "color": "Antraciet", "supplier": "Vconsyst", "lat": 52.99410860873246, "lng": 6.569226919641888}, {"id": 126, "number": "207", "street": "Zuidhage", "type": "Restafval", "subtype": "60L", "condition": "Goed", "color": "Antraciet", "supplier": "Vconsyst", "lat": 52.991273221660286, "lng": 6.565856353559293}, {"id": 127, "number": "214", "street": "Burgemeester Agterstraat", "type": "Restafval", "subtype": "60L", "condition": "Redelijk", "color": "Antraciet", "supplier": "Vconsyst", "lat": 52.99619097048462, "lng": 6.555581211337112}, {"id": 128, "number": "201", "street": "Vogelkerslaan", "type": "Restafval", "subtype": "60L", "condition": "Goed", "color": "Antraciet", "supplier": "Vconsyst", "lat": 52.98788499016833, "lng": 6.566474103420615}, {"id": 129, "number": "254", "street": "Overcingellaan", "type": "Restafval", "subtype": "60L", "condition": "Redelijk", "color": "Antraciet", "supplier": "Vconsyst", "lat": 52.988710841742396, "lng": 6.56773546653859}, {"id": 130, "number": "291 ", "street": "Zwin", "type": "Papier", "subtype": "Klep", "condition": "Goed", "color": "Antraciet", "supplier": null, "lat": 52.99662029929862, "lng": 6.538566357186218}, {"id": 131, "number": "191", "street": "Zwin", "type": "Restafval", "subtype": "60L", "condition": "Slecht", "color": "Antraciet", "supplier": null, "lat": 52.99672607373256, "lng": 6.539039496253093}, {"id": 132, "number": "242", "street": "Ceresplein", "type": "Restafval", "subtype": "100L", "condition": "Slecht", "color": "Blauw", "supplier": "Vconsyst", "lat": 52.99695294352685, "lng": 6.559163695385146}, {"id": 133, "number": "274", "street": "Vaart NZ", "type": "Restafval", "subtype": "60L", "condition": "Goed", "color": "Antraciet", "supplier": "Vconsyst", "lat": 52.994547907989805, "lng": 6.549365601697973}, {"id": 134, "number": "173", "street": "Oostermoer", "type": "Restafval", "subtype": "60L", "condition": "Redelijk", "color": "Antraciet", "supplier": "Vconsyst", "lat": 53.005292775936496, "lng": 6.5469555852840475}, {"id": 135, "number": "172", "street": "Groen van Prinsterenlaan", "type": "Restafval", "subtype": "60L", "condition": "Redelijk", "color": "Antraciet", "supplier": "Vconsyst", "lat": 53.00734321531655, "lng": 6.549908242520079}, {"id": 136, "number": "171", "street": "Schultestraat", "type": "Restafval", "subtype": "60L", "condition": "Redelijk", "color": "Antraciet", "supplier": "Vconsyst", "lat": 53.00686701050508, "lng": 6.551633745382439}, {"id": 137, "number": "242", "street": "Ceresplein", "type": "Papier", "subtype": "Trommel", "condition": "Goed", "color": "Antraciet", "supplier": "Vconsyst", "lat": 52.99696973148854, "lng": 6.55915814469498}, {"id": 138, "number": "230", "street": "het Kanaal", "type": "Restafval", "subtype": "60L", "condition": "Goed", "color": "Antraciet", "supplier": "Vconsyst", "lat": 52.99863943794903, "lng": 6.561018381375235}, {"id": 139, "number": "235", "street": "het Kanaal", "type": "Papier", "subtype": "Klep", "condition": "Goed", "color": "Antraciet", "supplier": "Vconsyst", "lat": 52.99864476916685, "lng": 6.561044772979961}, {"id": 140, "number": "256", "street": "Javastraat", "type": "Restafval", "subtype": "100L", "condition": "Goed", "color": "Antraciet", "supplier": "Vconsyst", "lat": 52.99463600272007, "lng": 6.566562765342539}, {"id": 141, "number": "276", "street": "Het Kanaal", "type": "Restafval", "subtype": "100L", "condition": "Redelijk", "color": "Blauw", "supplier": "Vconsyst", "lat": 52.998377193226446, "lng": 6.559865908442724}, {"id": 142, "number": "305", "street": "Nijlandstraat", "type": "Restafval", "subtype": "60L", "condition": "Goed", "color": "Antraciet", "supplier": "Vconsyst", "lat": 52.99843829631073, "lng": 6.568947725946525}, {"id": 143, "number": "219", "street": "Korenmolen", "type": "Restafval", "subtype": "60L", "condition": "Redelijk", "color": "Antraciet", "supplier": "Vconsyst", "lat": 52.997763130001175, "lng": 6.562101898728215}, {"id": 144, "number": "233", "street": "Oranjestraat", "type": "Restafval", "subtype": "60L", "condition": "Goed", "color": "Antraciet", "supplier": "Vconsyst", "lat": 52.994279250150775, "lng": 6.566768981700832}, {"id": 145, "number": "212", "street": "Mercuriusprijs", "type": "Papier", "subtype": "Klep", "condition": "Goed", "color": "Antraciet", "supplier": "Vconsyst", "lat": 52.99580825634, "lng": 6.557925763024696}, {"id": 146, "number": "212", "street": "Mercuriusplein", "type": "Restafval", "subtype": "60L", "condition": "Redelijk", "color": "Antraciet", "supplier": "Vconsyst", "lat": 52.99581308237904, "lng": 6.557957887677565}, {"id": 147, "number": "228", "street": "Kloekhorststraat", "type": "Restafval", "subtype": "60L", "condition": "Goed", "color": "Antraciet", "supplier": "Vconsyst", "lat": 52.99748282707749, "lng": 6.5655769298952045}, {"id": 148, "number": "227", "street": "Jan Fabriciusstraat", "type": "Restafval", "subtype": "60L", "condition": "Goed", "color": "Antraciet", "supplier": "Vconsyst", "lat": 52.99790149610859, "lng": 6.567230616942177}, {"id": 149, "number": "226", "street": "Jan Fabriciusstraat", "type": "Restafval", "subtype": "60L", "condition": "Redelijk", "color": "Antraciet", "supplier": "Vconsyst", "lat": 52.998689116483305, "lng": 6.5670449800887205}, {"id": 150, "number": "703", "street": "Mercuriusplein", "type": "PMD", "subtype": "Pers", "condition": "Goed", "color": "Antraciet", "supplier": "de Rooij", "lat": 52.9958179716762, "lng": 6.557989999754043}, {"id": 151, "number": "263", "street": "Rolderstraat", "type": "Restafval", "subtype": "60L", "condition": "Redelijk", "color": "Antraciet", "supplier": "Vconsyst", "lat": 52.99606870326159, "lng": 6.5644238443116745}, {"id": 152, "number": "260", "street": "Prins Clausplantsoen", "type": "Restafval", "subtype": "60L", "condition": "Goed", "color": "Antraciet", "supplier": "Vconsyst", "lat": 52.989748691272794, "lng": 6.561596491278037}, {"id": 153, "number": "225", "street": "Cereshof", "type": "Restafval", "subtype": "100L", "condition": "Redelijk", "color": "Antraciet", "supplier": "Vconsyst", "lat": 52.99667268616597, "lng": 6.5611711650421425}, {"id": 154, "number": "208", "street": "Bellevue", "type": "Restafval", "subtype": "60L", "condition": "Goed", "color": "Antraciet", "supplier": "Vconsyst", "lat": 52.99098428112503, "lng": 6.554700160774442}, {"id": 155, "number": "202", "street": "Parkplein", "type": "Restafval", "subtype": "60L", "condition": "Goed", "color": "Antraciet", "supplier": "Vconsyst", "lat": 52.988572143899034, "lng": 6.565318109990513}, {"id": 156, "number": "241", "street": "Gedempte singel", "type": "Restafval", "subtype": "100L", "condition": "Redelijk", "color": "Antraciet", "supplier": "Vconsyst", "lat": 52.99522963543462, "lng": 6.561967697611298}, {"id": 157, "number": "240", "street": "Gedempte singel", "type": "Restafval", "subtype": "100L", "condition": "Redelijk", "color": "Antraciet", "supplier": "Vconsyst", "lat": 52.99522220974361, "lng": 6.562946047397352}, {"id": 158, "number": "232A", "street": "Javastraat", "type": "Restafval", "subtype": "60L", "condition": "Redelijk", "color": "Antraciet", "supplier": "Vconsyst", "lat": 52.99508847301363, "lng": 6.567173782330781}, {"id": 159, "number": "232", "street": "Javastraat", "type": "Restafval", "subtype": "60L", "condition": "Redelijk", "color": "Antraciet", "supplier": "Vconsyst", "lat": 52.99533000162825, "lng": 6.567072446078541}, {"id": 160, "number": "231", "street": "Doevenkamp", "type": "Restafval", "subtype": "60L", "condition": "Redelijk", "color": "Antraciet", "supplier": "Vconsyst", "lat": 52.99562124880325, "lng": 6.566141033266097}, {"id": 161, "number": "215", "street": "Kanaalstraat", "type": "Restafval", "subtype": "60L", "condition": "Redelijk", "color": "Antraciet", "supplier": "Vconsyst", "lat": 52.99664498375359, "lng": 6.557321663962434}, {"id": 162, "number": "222", "street": "Oude Molenstraat", "type": "Restafval", "subtype": "60L", "condition": "Goed", "color": "Antraciet", "supplier": "Vconsyst", "lat": 52.99820893331051, "lng": 6.56279546550123}, {"id": 163, "number": "224", "street": "Omloop", "type": "Restafval", "subtype": "60L", "condition": "Redelijk", "color": "Antraciet", "supplier": "Vconsyst", "lat": 52.997944705048695, "lng": 6.564071665194434}, {"id": 164, "number": "223", "street": "Omloop", "type": "Restafval", "subtype": "60L", "condition": "Redelijk", "color": "Antraciet", "supplier": "Vconsyst", "lat": 52.99782055863685, "lng": 6.563574877079373}, {"id": 165, "number": "217", "street": "Dreuplein", "type": "Restafval", "subtype": "60L", "condition": "Redelijk", "color": "Antraciet", "supplier": "Vconsyst", "lat": 52.99756670794094, "lng": 6.558310232084838}, {"id": 166, "number": "216", "street": "Kanaalstraat", "type": "Restafval", "subtype": "60L", "condition": "Redelijk", "color": "Antraciet", "supplier": "Vconsyst", "lat": 52.99700671461353, "lng": 6.556535007471502}, {"id": 167, "number": "143", "street": "Smetanalaan", "type": "PMD", "subtype": "60L", "condition": "Goed", "color": "Antraciet", "supplier": "de Rooij", "lat": 53.011172545149016, "lng": 6.5648296339867604}, {"id": 168, "number": "143", "street": "Smetanalaan", "type": "Papier", "subtype": "Klep", "condition": null, "color": "Antraciet", "supplier": "Vconsyst", "lat": 53.01115807488287, "lng": 6.564855273701617}, {"id": 169, "number": "143", "street": "Smetanalaan", "type": "Restafval", "subtype": "60L", "condition": "Redelijk", "color": "Antraciet", "supplier": "Vconsyst", "lat": 53.01118703324617, "lng": 6.5648094335709635}, {"id": 170, "number": "142", "street": "Smetanalaan", "type": "Restafval", "subtype": "60L", "condition": "Goed", "color": "Antraciet", "supplier": "Vconsyst", "lat": 53.01097355032401, "lng": 6.566143493751647}, {"id": 171, "number": "238", "street": "Molenstraat", "type": "Restafval", "subtype": "60L", "condition": "Redelijk", "color": "Antraciet", "supplier": "Vconsyst", "lat": 53.00646431862892, "lng": 6.5579769651992565}, {"id": 172, "number": "142", "street": "Smetanalaan", "type": "Papier", "subtype": "Klep", "condition": null, "color": "Antraciet", "supplier": "Vconsyst", "lat": 53.01094506311829, "lng": 6.566188912572428}, {"id": 173, "number": "142", "street": "Smetanalaan", "type": "PMD", "subtype": "Pers", "condition": "Goed", "color": "Antraciet", "supplier": "de Rooij", "lat": 53.01095940428054, "lng": 6.566166339705964}, {"id": 174, "number": "144", "street": "Smetanalaan", "type": "Papier", "subtype": "Klep", "condition": "Redelijk", "color": "Antraciet", "supplier": "Vconsyst", "lat": 53.01137011922279, "lng": 6.563516171277257}, {"id": 175, "number": "908", "street": "Paganinilaan ", "type": "Glas", "subtype": "Bruin/Groen", "condition": "Redelijk", "color": "Antraciet", "supplier": "Vconsyst", "lat": 53.00960923921988, "lng": 6.5636268652798275}, {"id": 176, "number": "237", "street": "Zwartwatersweg", "type": "Restafval", "subtype": "60L", "condition": "Redelijk", "color": "Antraciet", "supplier": "Vconsyst", "lat": 53.00656981651669, "lng": 6.559405116719423}, {"id": 177, "number": "154", "street": "Thorbeckelaan", "type": "Restafval", "subtype": "60L", "condition": "Redelijk", "color": "Antraciet", "supplier": "Vconsyst", "lat": 52.99998020580344, "lng": 6.55155064942203}, {"id": 178, "number": "907", "street": "Paganinilaan", "type": "Glas", "subtype": "Wit", "condition": "Slecht", "color": "Antraciet", "supplier": "Vconsyst", "lat": 53.00960185491776, "lng": 6.5636749269441355}, {"id": 179, "number": "144", "street": "Smetanalaan", "type": "PMD", "subtype": "60L", "condition": "Goed", "color": "Antraciet", "supplier": "de Rooij", "lat": 53.011384579148796, "lng": 6.563494211061815}, {"id": 180, "number": "144", "street": "Smetanalaan", "type": "Restafval", "subtype": "60L", "condition": "Redelijk", "color": "Antraciet", "supplier": "Vconsyst", "lat": 53.01139927796074, "lng": 6.563471796298837}, {"id": 181, "number": "264", "street": "Verdistraat", "type": "Restafval", "subtype": "60L", "condition": "Goed", "color": "Antraciet", "supplier": "Vconsyst", "lat": 53.009324950243055, "lng": 6.5627290090348245}, {"id": 182, "number": "163A", "street": "Troelstralaan", "type": "Restafval", "subtype": "60L", "condition": "Redelijk", "color": "Antraciet", "supplier": "Vconsyst", "lat": 53.00098157899074, "lng": 6.562365462635945}, {"id": 183, "number": "158", "street": "Kuyperstraat", "type": "Restafval", "subtype": "60L", "condition": "Goed", "color": "Antraciet", "supplier": "Vconsyst", "lat": 53.0018957449784, "lng": 6.562714651261617}, {"id": 184, "number": "161", "street": "Kuyperstraat", "type": "Restafval", "subtype": "60L", "condition": "Redelijk", "color": "Antraciet", "supplier": "Vconsyst", "lat": 53.00157842699578, "lng": 6.560325341913316}, {"id": 185, "number": "162", "street": "Troelstralaan", "type": "Restafval", "subtype": "60L", "condition": "Redelijk", "color": "Antraciet", "supplier": "Vconsyst", "lat": 53.00071642379015, "lng": 6.561125336589585}, {"id": 186, "number": "156", "street": "Schaperstraat", "type": "Restafval", "subtype": "60L", "condition": "Redelijk", "color": "Antraciet", "supplier": "Vconsyst", "lat": 53.001068612900994, "lng": 6.5561708547098485}, {"id": 187, "number": "164", "street": "Troelstralaan", "type": "Restafval", "subtype": "60L", "condition": "Redelijk", "color": "Antraciet", "supplier": "Vconsyst", "lat": 53.00070027520606, "lng": 6.56365411208069}, {"id": 188, "number": "163", "street": "Troelstralaan", "type": "Restafval", "subtype": "60L", "condition": "Redelijk", "color": "Antraciet", "supplier": "Vconsyst", "lat": 53.000662428644574, "lng": 6.561868445450492}, {"id": 189, "number": "910", "street": "Thorbeckelaan", "type": "Glas", "subtype": "Bruin/Groen", "condition": "Redelijk", "color": "Antraciet", "supplier": "Vconsyst", "lat": 53.00250003451878, "lng": 6.56125815699593}, {"id": 190, "number": "150", "street": "Echtenstraat", "type": "Restafval", "subtype": "60L", "condition": "Redelijk", "color": "Antraciet", "supplier": "Vconsyst", "lat": 53.003664463374164, "lng": 6.555816267209322}, {"id": 191, "number": "149", "street": "Molenstraat", "type": "Restafval", "subtype": "60L", "condition": "Goed", "color": "Antraciet", "supplier": "Vconsyst", "lat": 53.003872018868606, "lng": 6.556749038274479}, {"id": 192, "number": "148", "street": "Klenckestraat", "type": "Restafval", "subtype": "100L", "condition": "Redelijk", "color": "Antraciet", "supplier": "Vconsyst", "lat": 53.0045248314372, "lng": 6.550296518640387}, {"id": 193, "number": "151", "street": "Cort v/d Lindenstraat", "type": "Papier", "subtype": "Klep", "condition": "Redelijk", "color": "Antraciet", "supplier": "Vconsyst", "lat": 53.00325599310623, "lng": 6.559982563665533}, {"id": 194, "number": "909", "street": "Thorbeckelaan", "type": "Glas", "subtype": "Wit", "condition": "Redelijk", "color": "Antraciet", "supplier": "Vconsyst", "lat": 53.002516715449595, "lng": 6.561252573966436}, {"id": 195, "number": "151R", "street": "Cort v/d Londenstraat", "type": "Restafval", "subtype": "60L", "condition": "Goed", "color": "Antraciet", "supplier": "Vconsyst", "lat": 53.00326414341299, "lng": 6.560044952560315}, {"id": 196, "number": "751", "street": "Cort v/d Lindenstraat", "type": "PMD", "subtype": "Pers", "condition": "Goed", "color": "Antraciet", "supplier": "de Rooij", "lat": 53.003260124209696, "lng": 6.5600140199718275}, {"id": 197, "number": "153", "street": "Thorbeckelaan", "type": "Restafval", "subtype": "60L", "condition": "Redelijk", "color": "Antraciet", "supplier": "Vconsyst", "lat": 53.00044543806075, "lng": 6.552846079350533}, {"id": 198, "number": "186", "street": "Grift", "type": "Restafval", "subtype": "60L", "condition": "Slecht", "color": "Antraciet", "supplier": null, "lat": 52.99872678744605, "lng": 6.53516959622993}, {"id": 199, "number": "185", "street": "Gouwe", "type": "Restafval", "subtype": "60L", "condition": "Slecht", "color": "Antraciet", "supplier": null, "lat": 52.999591241562214, "lng": 6.53604086773243}, {"id": 200, "number": "170", "street": "van der Scheerstraat", "type": "Restafval", "subtype": "60L", "condition": "Redelijk", "color": "Antraciet", "supplier": "Vconsyst", "lat": 53.001940403041694, "lng": 6.5413331260404775}, {"id": 201, "number": "190 ", "street": "Stroom", "type": "Papier", "subtype": "Klep", "condition": "Redelijk", "color": "Antraciet", "supplier": null, "lat": 52.99769907996816, "lng": 6.538977669703694}, {"id": 202, "number": "189", "street": "Epe", "type": "Restafval", "subtype": "60L", "condition": "Redelijk", "color": "Antraciet", "supplier": null, "lat": 52.998138016692586, "lng": 6.538605910008187}, {"id": 203, "number": "109", "street": "Stroom", "type": "Restafval", "subtype": "60L", "condition": "Redelijk", "color": "Antraciet", "supplier": null, "lat": 52.99771139053156, "lng": 6.538996481324045}, {"id": 204, "number": "182", "street": "Maria in campislaan", "type": "Restafval", "subtype": "60L", "condition": "Redelijk", "color": "Antraciet", "supplier": null, "lat": 53.00049846740153, "lng": 6.544287538584573}, {"id": 205, "number": "174", "street": "Oostermoer", "type": "Restafval", "subtype": "60L", "condition": "Redelijk", "color": "Antraciet", "supplier": "Vconsyst", "lat": 53.004530387883676, "lng": 6.5481859843725365}, {"id": 206, "number": "173A", "street": "Oostermoer", "type": "Restafval", "subtype": "60L", "condition": "Redelijk", "color": "Antraciet", "supplier": "Vconsyst", "lat": 53.0048974031294, "lng": 6.54757253474645}, {"id": 207, "number": "175", "street": "Rabenhauptstraat", "type": "Restafval", "subtype": "60L", "condition": "Slecht", "color": "Antraciet", "supplier": "Vconsyst", "lat": 53.002057008757696, "lng": 6.54701783943156}, {"id": 208, "number": "181", "street": "Maria in campislaan", "type": "Restafval", "subtype": "60L", "condition": "Redelijk", "color": "Antraciet", "supplier": null, "lat": 53.000692700165935, "lng": 6.543239832570382}, {"id": 209, "number": "180", "street": "Maria in campislaan", "type": "Restafval", "subtype": "60L", "condition": "Redelijk", "color": "Antraciet", "supplier": null, "lat": 53.00088352135721, "lng": 6.5422615815990115}, {"id": 210, "number": "178", "street": "Stadhouderslaan", "type": "Restafval", "subtype": "100L", "condition": "Slecht", "color": "Blauw", "supplier": "Vconsyst", "lat": 53.001295378788484, "lng": 6.5480838962303585}, {"id": 211, "number": "197", "street": "Nobellaan", "type": "Restafval", "subtype": "60L", "condition": "Goed", "color": "Antraciet", "supplier": "Vconsyst", "lat": 52.997337366262116, "lng": 6.554724249997108}, {"id": 212, "number": "921", "street": "Nobellaan", "type": "Glas", "subtype": "Wit", "condition": "Slecht", "color": "Antraciet", "supplier": "Vconsyst", "lat": 53.0001737467465, "lng": 6.5487329784304755}, {"id": 213, "number": "922", "street": "Nobellaan", "type": "Glas", "subtype": "Bruin/Groen", "condition": "Slecht", "color": "Antraciet", "supplier": "Vconsyst", "lat": 53.000172932576646, "lng": 6.548701137645256}, {"id": 214, "number": "169", "street": "Nobellaan", "type": "Restafval", "subtype": "60L", "condition": "Goed", "color": "Antraciet", "supplier": "Vconsyst", "lat": 52.99780843138402, "lng": 6.554090687990143}, {"id": 215, "number": "155", "street": "Thorbeckelaan", "type": "Restafval", "subtype": "60L", "condition": "Redelijk", "color": "Antraciet", "supplier": "Vconsyst", "lat": 53.000060805665065, "lng": 6.552635755894742}, {"id": 216, "number": "155A", "street": "Thorbeckelaan", "type": "Restafval", "subtype": "60L", "condition": "Redelijk", "color": "Antraciet", "supplier": "Vconsyst", "lat": 53.000328038693326, "lng": 6.553310843424033}, {"id": 217, "number": "196", "street": "Troelstralaan", "type": "Restafval", "subtype": "100L", "condition": "Slecht", "color": "Antraciet", "supplier": "Vconsyst", "lat": 52.997720552356476, "lng": 6.5536831313289}, {"id": 218, "number": "198", "street": "Einsteinlaan", "type": "Restafval", "subtype": "60L", "condition": "Redelijk", "color": "Antraciet", "supplier": "Vconsyst", "lat": 52.996960302419396, "lng": 6.553332542229722}, {"id": 219, "number": "170", "street": "Schultestraat", "type": "Restafval", "subtype": "60L", "condition": "Redelijk", "color": "Antraciet", "supplier": "Vconsyst", "lat": 53.007591744364156, "lng": 6.552485377017865}, {"id": 220, "number": "200", "street": "Sluisstraat", "type": "Restafval", "subtype": "60L", "condition": "Redelijk", "color": "Antraciet", "supplier": "Vconsyst", "lat": 52.995023785334, "lng": 6.551142224089894}, {"id": 221, "number": "199", "street": "Troelstralaan", "type": "Restafval", "subtype": "60L", "condition": "Redelijk", "color": "Antraciet", "supplier": "Vconsyst", "lat": 52.996973946995446, "lng": 6.552449354574956}, {"id": 222, "number": "194", "street": "Einsteinlaan", "type": "Restafval", "subtype": "60L", "condition": "Redelijk", "color": "Antraciet", "supplier": "Vconsyst", "lat": 52.998422673457334, "lng": 6.551229248383042}, {"id": 223, "number": "195", "street": "Einsteinlaan", "type": "Restafval", "subtype": "60L", "condition": "Redelijk", "color": "Antraciet", "supplier": "Vconsyst", "lat": 52.998104127557376, "lng": 6.551821872365848}, {"id": 224, "number": "287", "street": "van Houtenstraat", "type": "Papier", "subtype": "Klep", "condition": "Goed", "color": "Antraciet", "supplier": "Vconsyst", "lat": 52.999845913453555, "lng": 6.5634992038981474}, {"id": 225, "number": "0000", "street": "Thorbeckelaan", "type": "Kleding", "subtype": "Klep", "condition": null, "color": null, "supplier": "Sympany", "lat": 53.002534787847246, "lng": 6.561247281092803}, {"id": 226, "number": "304", "street": "Smetanalaan", "type": "Restafval", "subtype": "60L", "condition": "Goed", "color": "Antraciet", "supplier": "Vconsyst", "lat": 53.01170908901005, "lng": 6.56276784140792}, {"id": 227, "number": "0000", "street": "Paganinilaan", "type": "Kleding", "subtype": "Klep", "condition": "Redelijk", "color": null, "supplier": "Sympany", "lat": 53.00959751146439, "lng": 6.563704833656604}, {"id": 228, "number": "282", "street": "Troelstralaan", "type": "Restafval", "subtype": "60L", "condition": "Goed", "color": "Antraciet", "supplier": "Vconsyst", "lat": 52.998357710720725, "lng": 6.553540794170439}, {"id": 229, "number": "334", "street": "Prins Bernhardstraat", "type": "Restafval", "subtype": "60L", "condition": "Goed", "color": "Antraciet", "supplier": "Wastevision", "lat": 52.99899693895438, "lng": 6.560057077121706}, {"id": 230, "number": "734", "street": "Prins Bernhardstraat", "type": "PMD", "subtype": "60L", "condition": "Goed", "color": "Antraciet", "supplier": "Wastevision", "lat": 52.9989678134664, "lng": 6.560081544535116}, {"id": 231, "number": "334", "street": "Prins Bernhardstraat", "type": "Papier", "subtype": "Klep", "condition": "Goed", "color": "Antraciet", "supplier": "Wastevision", "lat": 52.99894246590148, "lng": 6.560103057389539}, {"id": 232, "number": "312", "street": "Nijlandstraat", "type": "Restafval", "subtype": "60L", "condition": "Goed", "color": "Antraciet", "supplier": "Vconsyst", "lat": 52.998379831008734, "lng": 6.567544313130992}, {"id": 233, "number": "914", "street": "Kloekhorststraat", "type": "Glas", "subtype": "Bruin/Groen", "condition": "Goed", "color": "Antraciet", "supplier": "Vconsyst", "lat": 52.997314866982784, "lng": 6.566050494763536}, {"id": 234, "number": "913", "street": "Kloekhorststraat", "type": "Glas", "subtype": "Wit", "condition": "Goed", "color": "Antraciet", "supplier": "Vconsyst", "lat": 52.997317204767384, "lng": 6.566017821240043}, {"id": 235, "number": "320", "street": "Groningerstraat", "type": "Papier", "subtype": "Trommel", "condition": "Goed", "color": "Antraciet", "supplier": "Vconsyst", "lat": 52.998039092435874, "lng": 6.56530321771973}, {"id": 236, "number": "320", "street": "Groningerstraat", "type": "Restafval", "subtype": "100L", "condition": "Goed", "color": "Antraciet", "supplier": "Vconsyst", "lat": 52.998056295730485, "lng": 6.56531442330459}, {"id": 237, "number": "319", "street": "Groningerstraat", "type": "Restafval", "subtype": "100L", "condition": "Goed", "color": "Antraciet", "supplier": "Vconsyst", "lat": 52.99720269264045, "lng": 6.5643530867117}, {"id": 238, "number": "319", "street": "Groningerstraat", "type": "Papier", "subtype": "Trommel", "condition": "Goed", "color": "Antraciet", "supplier": "Vconsyst", "lat": 52.99718999049802, "lng": 6.564330963901214}, {"id": 239, "number": null, "street": "Mening", "type": "Glas", "subtype": "Wit", "condition": "Goed", "color": "Antraciet", "supplier": "Vconsyst", "lat": 52.995377946232736, "lng": 6.565214815410934}, {"id": 240, "number": null, "street": "Menning", "type": "Glas", "subtype": "Bruin/Groen", "condition": "Goed", "color": "Antraciet", "supplier": "Vconsyst", "lat": 52.995350271645734, "lng": 6.565194752437359}, {"id": 241, "number": "0000", "street": "Menning", "type": "Kleding", "subtype": "Klep", "condition": null, "color": null, "supplier": "Sympany", "lat": 52.9953992418925, "lng": 6.565231313869425}, {"id": 242, "number": "324", "street": "W.A. Scholtenstraat", "type": "Restafval", "subtype": "100L", "condition": "Goed", "color": "Antraciet", "supplier": "Vconsyst", "lat": 53.00541204130244, "lng": 6.573775986444026}, {"id": 243, "number": "306", "street": "Jan Fabriciusstraat", "type": "Restafval", "subtype": "100L", "condition": "Goed", "color": "Antraciet", "supplier": "Vconsyst", "lat": 52.9966950398014, "lng": 6.567272049039705}, {"id": 244, "number": "307", "street": "Jan Fabriciusstraat", "type": "Restafval", "subtype": "100L", "condition": "Goed", "color": "Antraciet", "supplier": "Vconsyst", "lat": 52.996612548368184, "lng": 6.5672568181040845}, {"id": 245, "number": "706", "street": "Jan Fabriciusstraat", "type": "PMD", "subtype": "Pers", "condition": "Goed", "color": "Antraciet", "supplier": "de Rooij", "lat": 52.996530780184536, "lng": 6.567247160316456}, {"id": 246, "number": "307", "street": "Jan Fabriciusstraat", "type": "Papier", "subtype": "Trommel", "condition": "Goed", "color": "Antraciet", "supplier": "Vconsyst", "lat": 52.996460693432994, "lng": 6.567233531076959}, {"id": 247, "number": "0000", "street": "Jan Fabriciusstraat", "type": "Kleding", "subtype": "Klep", "condition": "Redelijk", "color": null, "supplier": "Sympany", "lat": 52.99639962864064, "lng": 6.567206253733362}, {"id": 248, "number": "301", "street": "Kruisstraat", "type": "Restafval", "subtype": "100L", "condition": "Redelijk", "color": "Antraciet", "supplier": "Vconsyst", "lat": 52.99431567055824, "lng": 6.5615551427238055}, {"id": 249, "number": "243", "street": "Markt", "type": "Restafval", "subtype": "100L", "condition": "Redelijk", "color": "Antraciet", "supplier": "de Rooij", "lat": 52.993646147947565, "lng": 6.559896585011373}, {"id": 250, "number": "300", "street": "Marktstraat", "type": "Restafval", "subtype": "100L", "condition": "Redelijk", "color": "Antraciet", "supplier": "de Rooij", "lat": 52.9939157213384, "lng": 6.5608894120465475}, {"id": 251, "number": "302", "street": "Weiersloop", "type": "Restafval", "subtype": "100L", "condition": "Redelijk", "color": "Blauw", "supplier": "Vconsyst", "lat": 52.99465850880208, "lng": 6.5602002694763035}, {"id": 252, "number": "213", "street": "Weierstraat", "type": "Papier", "subtype": "Trommel", "condition": "Goed", "color": "Antraciet", "supplier": "Vconsyst", "lat": 52.9954867979946, "lng": 6.557729433524424}, {"id": 253, "number": "213", "street": "Weierstraat", "type": "Restafval", "subtype": "100L", "condition": "Goed", "color": "Antraciet", "supplier": "Vconsyst", "lat": 52.99547826179879, "lng": 6.557647644612725}, {"id": 254, "number": "209", "street": "Alteveerstraat", "type": "Restafval", "subtype": "100L", "condition": "Goed", "color": "Antraciet", "supplier": "Vconsyst", "lat": 52.99506378658749, "lng": 6.5571351898791175}, {"id": 255, "number": "722", "street": "Oude Molenstraat", "type": "PMD", "subtype": "Pers", "condition": "Goed", "color": "Antraciet", "supplier": "de Rooij", "lat": 52.998258370673476, "lng": 6.562811266867075}, {"id": 256, "number": "221", "street": "het Kanaal", "type": "Restafval", "subtype": "60L", "condition": "Slecht", "color": "Antraciet", "supplier": "Vconsyst", "lat": 52.99896910828136, "lng": 6.564550628039324}, {"id": 257, "number": "221", "street": "het Kanaal", "type": "Papier", "subtype": "Klep", "condition": "Goed", "color": "Antraciet", "supplier": "Vconsyst", "lat": 52.99896410634878, "lng": 6.564474840772032}, {"id": 258, "number": "327", "street": "Torenhaan", "type": "Restafval", "subtype": "Trommel", "condition": "Goed", "color": "Antraciet", "supplier": "Wastevision", "lat": 52.99275409375201, "lng": 6.561647708723947}, {"id": 259, "number": "236", "street": "Brink", "type": "Restafval", "subtype": "100L", "condition": "Redelijk", "color": "Blauw", "supplier": "Vconsyst", "lat": 52.99331246334539, "lng": 6.562985440319168}, {"id": 260, "number": "318", "street": "Ulohof", "type": "Restafval", "subtype": "100L", "condition": "Goed", "color": "Antraciet", "supplier": "Vconsyst", "lat": 52.992772136712226, "lng": 6.558359009706465}, {"id": 261, "number": "314", "street": "Heuven Goedhartlaan", "type": "Restafval", "subtype": "60L", "condition": "Goed", "color": "Antraciet", "supplier": "Vconsyst", "lat": 52.998624392027864, "lng": 6.549483607088652}, {"id": 262, "number": "313", "street": "Heuven Goedhartlaan", "type": "Papier", "subtype": "Trommel", "condition": "Goed", "color": "Antraciet", "supplier": "Vconsyst", "lat": 52.9985201273807, "lng": 6.5479789972596985}, {"id": 263, "number": "193", "street": "Heuven Goedhartlaan", "type": "Restafval", "subtype": "60L", "condition": "Redelijk", "color": "Antraciet", "supplier": "Vconsyst", "lat": 52.998544198747595, "lng": 6.5478657915676095}, {"id": 264, "number": "700", "street": "Nobellaan", "type": "PMD", "subtype": "60L", "condition": "Goed", "color": "Antraciet", "supplier": "de Rooij", "lat": 53.00019180120342, "lng": 6.548852697806717}, {"id": 265, "number": "0000", "street": "Nobellaan", "type": "Kleding", "subtype": "60L", "condition": "Goed", "color": "Antraciet", "supplier": "Wastevision", "lat": 53.00017359212994, "lng": 6.548852009697207}, {"id": 266, "number": "311", "street": "Stadhouderschap", "type": "Restafval", "subtype": "60L", "condition": "Goed", "color": "Antraciet", "supplier": "Vconsyst", "lat": 53.00178169747404, "lng": 6.55184576665411}, {"id": 267, "number": "310", "street": "Amstelstraat", "type": "Restafval", "subtype": "100L", "condition": "Goed", "color": "Antraciet", "supplier": "Vconsyst", "lat": 53.00829078885876, "lng": 6.5418997150497376}, {"id": 268, "number": "310", "street": "Amstelstraat", "type": "Papier", "subtype": "Klep", "condition": "Goed", "color": "Antraciet", "supplier": "Vconsyst", "lat": 53.008275914401416, "lng": 6.541872602097842}, {"id": 269, "number": "322", "street": "Beuzeveen", "type": "Restafval", "subtype": "60L", "condition": "Goed", "color": "Antraciet", "supplier": "Vconsyst", "lat": 53.01613877948067, "lng": 6.557073712774356}, {"id": 270, "number": "322", "street": "Beuzeveen", "type": "Papier", "subtype": "Klep", "condition": "Goed", "color": "Antraciet", "supplier": "Vconsyst", "lat": 53.01614837026952, "lng": 6.557044939735792}, {"id": 271, "number": "325", "street": "Hoogbree", "type": "Restafval", "subtype": "100L", "condition": "Goed", "color": "Antraciet", "supplier": "Vconsyst", "lat": 53.0213449921606, "lng": 6.57331587115214}, {"id": 272, "number": "325", "street": "Hoekbree", "type": "Papier", "subtype": "Klep", "condition": "Goed", "color": "Antraciet", "supplier": "Vconsyst", "lat": 53.021368685522894, "lng": 6.573290956377742}, {"id": 273, "number": "272", "street": "het Palet", "type": "Restafval", "subtype": "60L", "condition": "Goed", "color": "Antraciet", "supplier": "Vconsyst", "lat": 52.99664391540619, "lng": 6.577151794196321}, {"id": 274, "number": "099", "street": "Roerdompstraat", "type": "Restafval", "subtype": "100L", "condition": "Redelijk", "color": "Blauw", "supplier": "Vconsyst", "lat": 52.991902829905214, "lng": 6.58008017715672}, {"id": 275, "number": "326", "street": "Roerdompstraat", "type": "Papier", "subtype": "Klep", "condition": "Goed", "color": "Antraciet", "supplier": "Vconsyst", "lat": 52.99188638333165, "lng": 6.580126187967255}, {"id": 276, "number": "136", "street": "Oosterpark", "type": "Papier", "subtype": "Trommel", "condition": "Redelijk", "color": "Antraciet", "supplier": "Vconsyst", "lat": 52.99306639611169, "lng": 6.575743394832632}, {"id": 277, "number": "736", "street": "Oosterpark", "type": "PMD", "subtype": "Pers", "condition": "Goed", "color": "Antraciet", "supplier": "de Rooij", "lat": 52.99310008968016, "lng": 6.575628811124866}, {"id": 278, "number": "140", "street": "Koekoekstraat", "type": "Restafval", "subtype": "60L", "condition": "Redelijk", "color": "Antraciet", "supplier": "Vconsyst", "lat": 52.99397244569903, "lng": 6.572635096388792}, {"id": 279, "number": "739", "street": "Oosterpark", "type": "PMD", "subtype": "Pers", "condition": "Goed", "color": "Antraciet", "supplier": "de Rooij", "lat": 52.992531380528945, "lng": 6.575448849827372}, {"id": 280, "number": "139", "street": "Oosterpark", "type": "Papier", "subtype": "Trommel", "condition": "Redelijk", "color": "Antraciet", "supplier": "Vconsyst", "lat": 52.99252053057757, "lng": 6.57547230663608}, {"id": 281, "number": "329", "street": "Sperwerstraat", "type": "Papier", "subtype": "Trommel", "condition": "Redelijk", "color": "Antraciet", "supplier": "Vconsyst", "lat": 52.99230111614005, "lng": 6.576709319121667}, {"id": 282, "number": "329", "street": "Sperwerstraat", "type": "Restafval", "subtype": "60L", "condition": "Redelijk", "color": "Antraciet", "supplier": "Vconsyst", "lat": 52.99227324492331, "lng": 6.576688369510925}, {"id": 283, "number": "729", "street": "Sperwerstraat", "type": "PMD", "subtype": "Trommel", "condition": "Goed", "color": "Antraciet", "supplier": "Wastevision", "lat": 52.992235283913224, "lng": 6.576665864018111}, {"id": 284, "number": "316", "street": "Middenweg", "type": "Restafval", "subtype": "100L", "condition": "Goed", "color": "Antraciet", "supplier": "Vconsyst", "lat": 52.97709952927744, "lng": 6.573417009775051}, {"id": 285, "number": null, "street": "Middenweg", "type": "PMD", "subtype": "Pers", "condition": "Goed", "color": "Antraciet", "supplier": "de Rooij", "lat": 52.976538011301066, "lng": 6.569940973393241}, {"id": 286, "number": "317", "street": "BBL weg", "type": "Restafval", "subtype": "100L", "condition": "Goed", "color": "Antraciet", "supplier": "Vconsyst", "lat": 52.9790026538747, "lng": 6.568972778163178}, {"id": 287, "number": "701", "street": "Wc Peels", "type": "PMD", "subtype": "60L", "condition": "Goed", "color": "Antraciet", "supplier": null, "lat": 53.01604055307842, "lng": 6.561119544252634}, {"id": 288, "number": "105", "street": "Winkelakker", "type": "Restafval", "subtype": "60L", "condition": "Redelijk", "color": "Antraciet", "supplier": null, "lat": 53.0160758964509, "lng": 6.561995598385714}, {"id": 289, "number": "315", "street": "Zuringes", "type": "Restafval", "subtype": "60L", "condition": "Redelijk", "color": "Antraciet", "supplier": null, "lat": 53.01566555162802, "lng": 6.564253270408916}, {"id": 290, "number": "315", "street": "Zuringes", "type": "Papier", "subtype": "60L", "condition": "Goed", "color": "Antraciet", "supplier": null, "lat": 53.01566179568479, "lng": 6.564253715074978}, {"id": 291, "number": "187", "street": "Eem", "type": "Restafval", "subtype": "60L", "condition": "Slecht", "color": "Antraciet", "supplier": null, "lat": 52.999660720977516, "lng": 6.541183580800206}, {"id": 292, "number": "188", "street": "Ellen", "type": "Restafval", "subtype": "60L", "condition": "Redelijk", "color": "Antraciet", "supplier": null, "lat": 52.99889947583514, "lng": 6.539929073624445}, {"id": 293, "number": "184", "street": "Gouwe", "type": "Restafval", "subtype": "60L", "condition": "Slecht", "color": "Antraciet", "supplier": null, "lat": 53.000443592404274, "lng": 6.537217435277488}, {"id": 294, "number": "183", "street": "Gouwe", "type": "Restafval", "subtype": "60L", "condition": "Slecht", "color": "Antraciet", "supplier": null, "lat": 53.00120036763405, "lng": 6.538509722899144}, {"id": 295, "number": "791", "street": "Zwin", "type": "PMD", "subtype": "60L", "condition": "Goed", "color": "Antraciet", "supplier": null, "lat": 52.996704853879045, "lng": 6.53900253507075}, {"id": 296, "number": "928", "street": "Zwin", "type": "Glas", "subtype": "Bruin/Groen", "condition": "Redelijk", "color": "Antraciet", "supplier": null, "lat": 52.99668170601742, "lng": 6.5390483581333925}, {"id": 297, "number": "927", "street": "Zwin", "type": "Glas", "subtype": "Wit", "condition": "Slecht", "color": "Antraciet", "supplier": null, "lat": 52.99670427861588, "lng": 6.53908304567978}, {"id": 298, "number": "323", "street": "Slingeborg", "type": "Restafval", "subtype": "100L", "condition": "Goed", "color": "Antraciet", "supplier": null, "lat": 52.9964203506922, "lng": 6.540223092216942}, {"id": 299, "number": "702", "street": "De hoogspanningsnet", "type": "PMD", "subtype": "60L", "condition": "Goed", "color": "Antraciet", "supplier": null, "lat": 53.00156575587362, "lng": 6.525487310654268}, {"id": 300, "number": "901", "street": "De hoogspanningsnet", "type": "Glas", "subtype": "Wit", "condition": "Slecht", "color": "Antraciet", "supplier": null, "lat": 53.001544301074986, "lng": 6.525488657228852}, {"id": 301, "number": "918", "street": "De hoogspanningweg", "type": "Glas", "subtype": "Bruin/Groen", "condition": "Slecht", "color": "Antraciet", "supplier": null, "lat": 53.00152390476158, "lng": 6.525497079832969}, {"id": 302, "number": null, "street": "Het sticht ", "type": "Kleding", "subtype": "Klep", "condition": null, "color": null, "supplier": null, "lat": 52.98372594594623, "lng": 6.53528209764286}, {"id": 303, "number": "704", "street": "Zuiderpoort", "type": "PMD", "subtype": "60L", "condition": "Goed", "color": "Antraciet", "supplier": "de Rooij", "lat": 52.9994841215004, "lng": 6.513225386976079}, {"id": 304, "number": null, "street": "Zuiderkade", "type": "Kleding", "subtype": "Klep", "condition": null, "color": null, "supplier": "Sympany", "lat": 52.999149500764695, "lng": 6.51347418437719}, {"id": 305, "number": null, "street": "Schoolstraat", "type": "Kleding", "subtype": "Klep", "condition": null, "color": null, "supplier": null, "lat": 53.001044715935556, "lng": 6.51505876402932}, {"id": 306, "number": null, "street": "Hoogspringen ", "type": "Kleding", "subtype": "Klep", "condition": null, "color": null, "supplier": null, "lat": 53.00142222308403, "lng": 6.525567165493117}, {"id": 308, "number": "106", "street": "Walakker", "type": "Papier", "subtype": "Klep", "condition": "Goed", "color": "Antraciet", "supplier": null, "lat": 53.01633825847908, "lng": 6.559428968786854}, {"id": 309, "number": "332", "street": "Vredeveldseweg", "type": "Papier", "subtype": "Klep", "condition": "Goed", "color": "Antraciet", "supplier": "Wastevision", "lat": 52.9897189895979, "lng": 6.579992507873187}, {"id": 310, "number": "332", "street": "Vredeveldseweg", "type": "Restafval", "subtype": "60L", "condition": "Goed", "color": "Antraciet", "supplier": "Wastevision", "lat": 52.98970596080501, "lng": 6.5800278080705965}, {"id": 311, "number": "732", "street": "Vredeveldseweg", "type": "PMD", "subtype": "60L", "condition": "Goed", "color": "Antraciet", "supplier": "Wastevision", "lat": 52.98965060921014, "lng": 6.580145480186317}, {"id": 312, "number": "791", "street": "Vredeveldseweg", "type": "PMD", "subtype": "60L", "condition": "Goed", "color": "Antraciet", "supplier": "de Rooij", "lat": 52.98885713356246, "lng": 6.581483584582369}, {"id": 313, "number": null, "street": "Vredeveldseweg", "type": "Kleding", "subtype": "Klep", "condition": "Goed", "color": null, "supplier": "Sympany", "lat": 52.98866133612783, "lng": 6.581786624056952}, {"id": 314, "number": "125", "street": "Vredeveldseweg", "type": "Restafval", "subtype": "60L", "condition": "Redelijk", "color": "Antraciet", "supplier": "Vconsyst", "lat": 52.988572431044076, "lng": 6.581910861060762}, {"id": 315, "number": "333", "street": "Brunelstraat", "type": "Papier", "subtype": "Klep", "condition": "Goed", "color": "Antraciet", "supplier": "Wastevision", "lat": 52.9875575573014, "lng": 6.577686947560519}, {"id": 316, "number": "333", "street": "Brunelstraat", "type": "Restafval", "subtype": "60L", "condition": "Goed", "color": "Antraciet", "supplier": "Wastevision", "lat": 52.98758535909744, "lng": 6.577721524614131}, {"id": 317, "number": "733", "street": "Brunelstraat", "type": "PMD", "subtype": "60L", "condition": "Goed", "color": "Antraciet", "supplier": "Wastevision", "lat": 52.987611534225245, "lng": 6.57775639901008}, {"id": 318, "number": null, "street": "Speenkruidstraat", "type": "Glas", "subtype": "Drie Kleuren", "condition": "Goed", "color": "Antraciet", "supplier": "Wastevision", "lat": 52.98562962125078, "lng": 6.581298418446126}, {"id": 319, "number": "177", "street": "Stadhouderslaan", "type": "Papier", "subtype": "Klep", "condition": "Goed", "color": "Antraciet", "supplier": null, "lat": 53.00153852259799, "lng": 6.548393934479328}, {"id": 320, "number": "177", "street": "Stadhouderslaan", "type": "Restafval", "subtype": "60L", "condition": "Redelijk", "color": "Antraciet", "supplier": null, "lat": 53.0015421981397, "lng": 6.54841444571222}, {"id": 321, "number": null, "street": "Westerloo", "type": "Glas", "subtype": "Wit", "condition": "Slecht", "color": "Antraciet", "supplier": null, "lat": 52.986598248370555, "lng": 6.531354804256173}, {"id": 322, "number": null, "street": "Westerloo", "type": "Glas", "subtype": "Bruin/Groen", "condition": "Redelijk", "color": "Antraciet", "supplier": null, "lat": 52.98659075251537, "lng": 6.53134069441803}, {"id": 323, "number": null, "street": "Westerloo", "type": "Kleding", "subtype": null, "condition": null, "color": null, "supplier": null, "lat": 52.98658457077275, "lng": 6.531327191840991}, {"id": 324, "number": "335", "street": "Nicolaas beetslaan", "type": "Papier", "subtype": "Klep", "condition": "Goed", "color": "Antraciet", "supplier": null, "lat": 52.98774356688069, "lng": 6.536936863566477}, {"id": 325, "number": "735", "street": "Nicolaas beetslaan", "type": "PMD", "subtype": "60L", "condition": "Goed", "color": "Antraciet", "supplier": null, "lat": 52.98772622103957, "lng": 6.536954846041841}, {"id": 326, "number": "335", "street": "Nicolaas beetslaan", "type": "Restafval", "subtype": "60L", "condition": "Goed", "color": "Antraciet", "supplier": null, "lat": 52.987710350962494, "lng": 6.536972450326459}, {"id": 327, "number": null, "street": "Bremstraat", "type": "Glas", "subtype": "Wit", "condition": "Redelijk", "color": "Antraciet", "supplier": null, "lat": 52.988409488656934, "lng": 6.579895494314083}, {"id": 328, "number": null, "street": "Bremstraat", "type": "Glas", "subtype": "Bruin/Groen", "condition": "Goed", "color": "Antraciet", "supplier": null, "lat": 52.9884022013105, "lng": 6.579871470668437}, {"id": 329, "number": "279", "street": "Platslaan", "type": "Restafval", "subtype": "60L", "condition": "Redelijk", "color": "Antraciet", "supplier": "Vconsyst", "lat": 52.989749159560496, "lng": 6.5823149439367965}, {"id": 330, "number": "330", "street": "Rembrandtlaan", "type": "Papier", "subtype": "Klep", "condition": "Goed", "color": "Antraciet", "supplier": null, "lat": 52.9954274463115, "lng": 6.575153684086282}, {"id": 331, "number": "730", "street": "Rembrandtlaan", "type": "PMD", "subtype": "60L", "condition": "Goed", "color": "Antraciet", "supplier": null, "lat": 52.995409795910945, "lng": 6.575186901988851}, {"id": 332, "number": "330", "street": "Rembrandtlaan ", "type": "Restafval", "subtype": "60L", "condition": "Redelijk", "color": "Antraciet", "supplier": null, "lat": 52.99539852225103, "lng": 6.575152658210196}, {"id": 333, "number": "328", "street": "Abel tasmanplein", "type": "Papier", "subtype": "60L", "condition": "Redelijk", "color": "Antraciet", "supplier": null, "lat": 52.99616155330602, "lng": 6.569147185177285}, {"id": 334, "number": "328", "street": "Abel Tasmanplein", "type": "Restafval", "subtype": "60L", "condition": "Redelijk", "color": "Antraciet", "supplier": null, "lat": 52.99616200206022, "lng": 6.569175115596071}, {"id": 335, "number": "728", "street": "Abel Tasmanplein", "type": "PMD", "subtype": "60L", "condition": "Redelijk", "color": "Antraciet", "supplier": null, "lat": 52.99616320396446, "lng": 6.569187969589471}, {"id": 336, "number": "295", "street": "Traverse", "type": "Papier", "subtype": "60L", "condition": "Redelijk", "color": "Antraciet", "supplier": null, "lat": 52.99951696830746, "lng": 6.516285245564835}, {"id": 337, "number": "295", "street": "Traverse", "type": "Restafval", "subtype": "100L", "condition": "Slecht", "color": "Antraciet", "supplier": null, "lat": 52.99948338570828, "lng": 6.516247355524461}, {"id": 338, "number": "266", "street": "Vondellaan", "type": "Restafval", "subtype": "60L", "condition": "Redelijk", "color": "Antraciet", "supplier": "Vconsyst", "lat": 53.00193712649322, "lng": 6.567512731060536}, {"id": 339, "number": "766", "street": "Vondellaan", "type": "PMD", "subtype": "60L", "condition": "Goed", "color": "Antraciet", "supplier": "de Rooij", "lat": 53.00193760870428, "lng": 6.567502383366773}, {"id": 340, "number": "266", "street": "Vondellaan", "type": "Papier", "subtype": "Klep", "condition": "Goed", "color": "Antraciet", "supplier": "Vconsyst", "lat": 53.0019370221583, "lng": 6.567490250720539}, {"id": 341, "number": "267", "street": "Vondellaan ", "type": "Restafval", "subtype": "60L", "condition": "Redelijk", "color": "Antraciet", "supplier": "Vconsyst", "lat": 53.00181254286512, "lng": 6.568915624649847}, {"id": 342, "number": "767", "street": "Vondellaan ", "type": "PMD", "subtype": "60L", "condition": "Goed", "color": "Antraciet", "supplier": "Wastevision", "lat": 53.001797979721786, "lng": 6.568916342403758}, {"id": 343, "number": "268", "street": "Vondellaan ", "type": "Restafval", "subtype": "60L", "condition": "Redelijk", "color": "Antraciet", "supplier": "Vconsyst", "lat": 53.00100228262517, "lng": 6.5690674974250305}, {"id": 344, "number": "768", "street": "Vondellaan ", "type": "PMD", "subtype": "60L", "condition": "Goed", "color": "Antraciet", "supplier": "de Rooij", "lat": 53.00098828414311, "lng": 6.569071814728313}, {"id": 345, "number": "305", "street": "Nijlandstraat", "type": "Papier", "subtype": "Klep", "condition": "Goed", "color": "Antraciet", "supplier": "Vconsyst", "lat": 52.99843737614286, "lng": 6.568998432251056}, {"id": 346, "number": "705", "street": "Nijlandstraat", "type": "PMD", "subtype": "60L", "condition": "Goed", "color": "Antraciet", "supplier": "Vconsyst", "lat": 52.9984386417792, "lng": 6.568973136590986}, {"id": 347, "number": "336", "street": "Veemarkrstraat", "type": "Papier", "subtype": "Klep", "condition": "Goed", "color": "Antraciet", "supplier": "Wastevision", "lat": 52.99820583651269, "lng": 6.569926117055077}, {"id": 348, "number": "336", "street": "Veekarktstraat", "type": "Restafval", "subtype": "60L", "condition": "Goed", "color": "Antraciet", "supplier": "Wastevision", "lat": 52.998205731087445, "lng": 6.569959076242849}, {"id": 349, "number": "330bio", "street": "Rembrandtlaan", "type": "BIO", "subtype": "15L", "condition": "Goed", "color": "Antraciet", "supplier": "Kliko", "lat": 52.995378686420274, "lng": 6.5751977410610625}, {"id": 350, "number": "272BIO", "street": "Het Palet", "type": "BIO", "subtype": "15L", "condition": "Goed", "color": "Antraciet", "supplier": "Kliko", "lat": 52.996632386876186, "lng": 6.577201810594711}, {"id": 351, "number": "133bio", "street": "Gerard Doustraat", "type": "BIO", "subtype": "15L", "condition": "Goed", "color": "Antraciet", "supplier": "Kliko", "lat": 52.994478473334674, "lng": 6.5799468150662594}, {"id": 352, "number": "99bio", "street": "Roerdompstraat", "type": "BIO", "subtype": "15L", "condition": "Goed", "color": "Antraciet", "supplier": "Kliko", "lat": 52.991934089516626, "lng": 6.580093039234961}, {"id": 353, "number": "135bio", "street": "Sperwerstraat", "type": "BIO", "subtype": "15L", "condition": "Goed", "color": "Antraciet", "supplier": "Kliko", "lat": 52.992658665838285, "lng": 6.576963569296528}, {"id": 354, "number": "136bio", "street": "Oosterpark", "type": "BIO", "subtype": "15L", "condition": "Goed", "color": "Antraciet", "supplier": "Kliko", "lat": 52.99306413325515, "lng": 6.575794207138354}, {"id": 355, "number": "137bio", "street": "Oosterpark", "type": "BIO", "subtype": "15L", "condition": "Goed", "color": "Antraciet", "supplier": "Kliko", "lat": 52.993529043158325, "lng": 6.574377205507495}, {"id": 356, "number": "141bio", "street": "Steenwijk", "type": "BIO", "subtype": "15L", "condition": "Goed", "color": "Antraciet", "supplier": "Kliko", "lat": 52.99471996048417, "lng": 6.575204932074893}, {"id": 357, "number": "140bio", "street": "Koekoekstraat", "type": "BIO", "subtype": "15L", "condition": "Goed", "color": "Antraciet", "supplier": "Kliko", "lat": 52.993984366943046, "lng": 6.572588658878503}, {"id": 358, "number": "138bio", "street": "Oosterpark", "type": "BIO", "subtype": "15L", "condition": "Goed", "color": "Antraciet", "supplier": "Kliko", "lat": 52.99308290171354, "lng": 6.5739335419617175}, {"id": 359, "number": "139bio", "street": "Oosterpark", "type": "BIO", "subtype": "15L", "condition": "Goed", "color": "Antraciet", "supplier": "Kliko", "lat": 52.99250000617793, "lng": 6.575514252569948}, {"id": 360, "number": "252bio", "street": "Resedastraat", "type": "BIO", "subtype": "15L", "condition": "Goed", "color": "Antraciet", "supplier": "Kliko", "lat": 52.98994646993667, "lng": 6.574400179920897}, {"id": 361, "number": "132bio", "street": "Oosterparallelweg", "type": "BIO", "subtype": "15L", "condition": "Goed", "color": "Antraciet", "supplier": "Kliko", "lat": 52.99119095238353, "lng": 6.571436625222174}, {"id": 362, "number": "131bio", "street": "Lodewijk napoleonstraat", "type": "BIO", "subtype": "15L", "condition": "Goed", "color": "Antraciet", "supplier": "Kliko", "lat": 52.98823811455926, "lng": 6.572021953986582}, {"id": 363, "number": "130bio", "street": "Anemoonstraat", "type": "BIO", "subtype": "15L", "condition": "Goed", "color": "Antraciet", "supplier": "Kliko", "lat": 52.987669756157885, "lng": 6.570538210225044}, {"id": 364, "number": "129bio", "street": "Anemoonstraat", "type": "BIO", "subtype": "15L", "condition": "Goed", "color": "Antraciet", "supplier": "Kliko", "lat": 52.98702175531621, "lng": 6.570280002073037}, {"id": 365, "number": "127bio", "street": "Berkenstraat", "type": "BIO", "subtype": "15L", "condition": "Goed", "color": "Antraciet", "supplier": "Kliko", "lat": 52.98516875914646, "lng": 6.569245562378984}, {"id": 366, "number": "317bio", "street": "BBL-weg", "type": "BIO", "subtype": "15L", "condition": "Goed", "color": "Antraciet", "supplier": "Kliko", "lat": 52.97901486050958, "lng": 6.568937690866481}, {"id": 367, "number": "316bio", "street": "Middenweg", "type": "BIO", "subtype": "15L", "condition": "Goed", "color": "Antraciet", "supplier": "Kliko", "lat": 52.97707293723196, "lng": 6.573411610001863}, {"id": 368, "number": "297bio", "street": "Middenweg", "type": "BIO", "subtype": "15L", "condition": "Goed", "color": "Antraciet", "supplier": "Kliko", "lat": 52.97657459109294, "lng": 6.569947913777117}, {"id": 369, "number": null, "street": "Middenweg", "type": "Glas", "subtype": "Drie Kleuren", "condition": "Goed", "color": "Antraciet", "supplier": "Wastevision", "lat": 52.97651858277044, "lng": 6.569934340233172}, {"id": 370, "number": "298bio", "street": "Middenweg", "type": "BIO", "subtype": "15L", "condition": "Goed", "color": "Antraciet", "supplier": "Kliko", "lat": 52.976105538082265, "lng": 6.568251270191577}, {"id": 371, "number": "497bio", "street": "Lindelaan", "type": "BIO", "subtype": "15L", "condition": "Goed", "color": "Antraciet", "supplier": "Kliko", "lat": 52.98422998877956, "lng": 6.571521764849845}, {"id": 372, "number": "251bio", "street": "Lindelaan", "type": "BIO", "subtype": "15L", "condition": "Goed", "color": "Antraciet", "supplier": "Kliko", "lat": 52.985332595267906, "lng": 6.571326592379634}, {"id": 373, "number": "128bio", "street": "Anreperstraat", "type": "BIO", "subtype": "15L", "condition": "Goed", "color": "Antraciet", "supplier": "Kliko", "lat": 52.986122568048145, "lng": 6.570857864939141}, {"id": 374, "number": "250bio", "street": "Tuinstraat", "type": "BIO", "subtype": "15L", "condition": "Goed", "color": "Antraciet", "supplier": "Kliko", "lat": 52.98960592004976, "lng": 6.577215508106154}, {"id": 375, "number": "299bio", "street": "Bremstraat", "type": "BIO", "subtype": "15L", "condition": "Goed", "color": "Antraciet", "supplier": "Kliko", "lat": 52.98911248306278, "lng": 6.579197476388881}, {"id": 376, "number": "333bio", "street": "Brunelstraat", "type": "BIO", "subtype": "15L", "condition": "Goed", "color": "Antraciet", "supplier": "Kliko", "lat": 52.98763504331919, "lng": 6.577808800435568}, {"id": 377, "number": "118bio", "street": "Zilverschoonstraat", "type": "BIO", "subtype": "15L", "condition": "Goed", "color": "Antraciet", "supplier": "Kliko", "lat": 52.98582620198237, "lng": 6.577754049017306}, {"id": 378, "number": "117bio", "street": "Zilverschoonstraat", "type": "BIO", "subtype": "15L", "condition": "Goed", "color": "Antraciet", "supplier": "Kliko", "lat": 52.985544105614196, "lng": 6.578271148939239}, {"id": 379, "number": "116bio", "street": "Zilverschoonstraat ", "type": "BIO", "subtype": "15L", "condition": "Goed", "color": "Antraciet", "supplier": "Kliko", "lat": 52.98525353408342, "lng": 6.578786233041684}, {"id": 380, "number": "115bio", "street": "Zilverschoonstraat ", "type": "BIO", "subtype": "15L", "condition": "Goed", "color": "Antraciet", "supplier": "Kliko", "lat": 52.98494125905332, "lng": 6.57962381772103}, {"id": 381, "number": "114bio", "street": "Speenkruidstraat", "type": "BIO", "subtype": "15L", "condition": "Goed", "color": "Antraciet", "supplier": "Kliko", "lat": 52.98455855499588, "lng": 6.580213564399999}, {"id": 382, "number": "113bio", "street": "Speenkruidstraat", "type": "BIO", "subtype": "15L", "condition": "Goed", "color": "Antraciet", "supplier": "Kliko", "lat": 52.98520113011859, "lng": 6.58120155490567}, {"id": 383, "number": "112bio", "street": "Speenkruidstraat ", "type": "BIO", "subtype": "15L", "condition": "Goed", "color": "Antraciet", "supplier": "Kliko", "lat": 52.98584733686842, "lng": 6.582170734689283}, {"id": 384, "number": "120bio", "street": "Dotterbloemstraat", "type": "BIO", "subtype": "15L", "condition": "Goed", "color": "Antraciet", "supplier": "Kliko", "lat": 52.98697870579282, "lng": 6.580833218689734}, {"id": 385, "number": "121bio", "street": "Dotterbloemstraat", "type": "BIO", "subtype": "15L", "condition": "Goed", "color": "Antraciet", "supplier": "Kliko", "lat": 52.987333125185785, "lng": 6.58047527957487}, {"id": 386, "number": "122bio", "street": "Dotterbloemstraat ", "type": "BIO", "subtype": "15L", "condition": "Goed", "color": "Antraciet", "supplier": "Kliko", "lat": 52.987617672018146, "lng": 6.579996308645173}, {"id": 387, "number": "123bio", "street": "Dotterbloemstraat ", "type": "BIO", "subtype": "15L", "condition": "Goed", "color": "Antraciet", "supplier": "Kliko", "lat": 52.98789371551268, "lng": 6.5792064092360505}, {"id": 388, "number": "119bio", "street": "Bremstraat ", "type": "BIO", "subtype": "15L", "condition": "Goed", "color": "Antraciet", "supplier": "Kliko", "lat": 52.986505380468046, "lng": 6.582619451258571}, {"id": 389, "number": "126bio", "street": "Sleutelbloemstraat", "type": "BIO", "subtype": "15L", "condition": "Goed", "color": "Antraciet", "supplier": "Kliko", "lat": 52.98778593643149, "lng": 6.581805568627974}, {"id": 390, "number": "125bio", "street": "Vredeveldseweg", "type": "BIO", "subtype": "15L", "condition": "Goed", "color": "Antraciet", "supplier": "Kliko", "lat": 52.988594352477314, "lng": 6.581882680011986}, {"id": 391, "number": "291bio", "street": "Vredeveldseweg ", "type": "BIO", "subtype": "15L", "condition": "Goed", "color": "Antraciet", "supplier": "Kliko", "lat": 52.988885161100015, "lng": 6.581464767572134}, {"id": 392, "number": "279bio", "street": "Platslaan", "type": "BIO", "subtype": "15L", "condition": "Goed", "color": "Antraciet", "supplier": "Kliko", "lat": 52.98978474779269, "lng": 6.58228521329416}, {"id": 393, "number": "134bio", "street": "Gerard Doustraat", "type": "BIO", "subtype": "15L", "condition": "Goed", "color": "Antraciet", "supplier": "Kliko", "lat": 52.99451039612848, "lng": 6.580688638438019}, {"id": 394, "number": "226bio", "street": "Fabriciusstraat", "type": "BIO", "subtype": "15L", "condition": "Goed", "color": "Antraciet", "supplier": "Kliko", "lat": 52.99873108171424, "lng": 6.5670156905188914}, {"id": 395, "number": "227bio", "street": "Fabriciusstraat ", "type": "BIO", "subtype": "15L", "condition": "Goed", "color": "Antraciet", "supplier": "Kliko", "lat": 52.997948139768525, "lng": 6.567189525306146}, {"id": 396, "number": "228bio", "street": "Kloekhorststraat", "type": "BIO", "subtype": "15L", "condition": "Goed", "color": "Antraciet", "supplier": "Kliko", "lat": 52.99747199945557, "lng": 6.56564468263059}, {"id": 397, "number": "320bio", "street": "Groningerstraat", "type": "BIO", "subtype": "15L", "condition": "Goed", "color": "Antraciet", "supplier": "Kliko", "lat": 52.99809206634276, "lng": 6.565212750184072}, {"id": 398, "number": "312bio", "street": "Nijlandstraat", "type": "BIO", "subtype": "15L", "condition": "Goed", "color": "Antraciet", "supplier": "Kliko", "lat": 52.99837958772078, "lng": 6.567589699612377}, {"id": 399, "number": "305bio", "street": "Nijlandstraat", "type": "BIO", "subtype": "15L", "condition": "Goed", "color": "Antraciet", "supplier": "Kliko", "lat": 52.99843829631073, "lng": 6.568947725946523}, {"id": 400, "number": "336bio", "street": "Veemarktstraat", "type": "BIO", "subtype": "15L", "condition": "Goed", "color": "Antraciet", "supplier": "Kliko", "lat": 52.99821850105197, "lng": 6.569923382583346}, {"id": 401, "number": "306bio", "street": "Jan Fabriciusstraat", "type": "BIO", "subtype": "15L", "condition": "Goed", "color": "Antraciet", "supplier": "Kliko", "lat": 52.99642753828484, "lng": 6.567235499285766}, {"id": 402, "number": "328bio", "street": "Abel Tasmanplein", "type": "BIO", "subtype": "15L", "condition": "Goed", "color": "Antraciet", "supplier": "Kliko", "lat": 52.996123448111426, "lng": 6.569189494030513}, {"id": 403, "number": "319bio", "street": "Groningerstraat", "type": "BIO", "subtype": "15L", "condition": "Goed", "color": "Antraciet", "supplier": "Kliko", "lat": 52.997172029941204, "lng": 6.564320417679756}, {"id": 404, "number": null, "street": null, "type": "BIO", "subtype": null, "condition": null, "color": null, "supplier": null, "lat": 52.99795215946641, "lng": 6.564060235030767}, {"id": 405, "number": "224bio", "street": "Omloop", "type": "BIO", "subtype": "15L", "condition": "Goed", "color": "Antraciet", "supplier": "Kliko", "lat": 52.99795215946641, "lng": 6.564060235030767}, {"id": 406, "number": "223bio", "street": "Omloop", "type": "BIO", "subtype": "15L", "condition": "Goed", "color": "Antraciet", "supplier": "Kliko", "lat": 52.99785099326334, "lng": 6.563588695863389}, {"id": 407, "number": "222bio", "street": "Oude Molenstraat", "type": "BIO", "subtype": "15L", "condition": "Goed", "color": "Antraciet", "supplier": "Kliko", "lat": 52.99895065702939, "lng": 6.564345256097368}, {"id": 408, "number": "230bio", "street": "Het Kanaal", "type": "BIO", "subtype": "15L", "condition": "Goed", "color": "Antraciet", "supplier": "Kliko", "lat": 52.99864335107705, "lng": 6.561073660104558}, {"id": 409, "number": "219bio", "street": "Stelling", "type": "BIO", "subtype": "15L", "condition": "Goed", "color": "Antraciet", "supplier": "Kliko", "lat": 52.997766427410994, "lng": 6.562027104997681}, {"id": 410, "number": "225bio", "street": "Cereshof", "type": "BIO", "subtype": "15L", "condition": "Goed", "color": "Antraciet", "supplier": "Kliko", "lat": 52.99664893328674, "lng": 6.561159867829112}, {"id": 411, "number": null, "street": null, "type": "BIO", "subtype": null, "condition": null, "color": null, "supplier": null, "lat": 53.00194541219777, "lng": 6.567569994168313}, {"id": 412, "number": "266", "street": "Vondellaan", "type": "BIO", "subtype": "15L", "condition": "Goed", "color": "Antraciet", "supplier": "Kliko", "lat": 53.00194541219777, "lng": 6.567569994168313}, {"id": 413, "number": "269bio", "street": "Huygensstraat", "type": "BIO", "subtype": "15L", "condition": "Goed", "color": "Antraciet", "supplier": "Kliko", "lat": 53.00159584782307, "lng": 6.566747858715251}, {"id": 414, "number": "270bio", "street": "Huygensstraat ", "type": "BIO", "subtype": "15L", "condition": "Goed", "color": "Antraciet", "supplier": "Kliko", "lat": 53.00067869725861, "lng": 6.566888171071053}, {"id": 415, "number": "268bio", "street": "Vondellaan ", "type": "BIO", "subtype": "15L", "condition": "Goed", "color": "Antraciet", "supplier": "Kliko", "lat": 53.00096875253902, "lng": 6.569093399447937}, {"id": 416, "number": "267bio", "street": "Vondellaan ", "type": "BIO", "subtype": "15L", "condition": "Goed", "color": "Antraciet", "supplier": "Kliko", "lat": 53.00184411479594, "lng": 6.56890090216065}, {"id": 417, "number": "278bio", "street": "Anne de Vriesestraat", "type": "BIO", "subtype": "15L", "condition": "Goed", "color": "Antraciet", "supplier": "Kliko", "lat": 53.000052268210986, "lng": 6.567353846036244}, {"id": 418, "number": "163bio", "street": "Troelstralaan ", "type": "BIO", "subtype": "15L", "condition": "Goed", "color": "Antraciet", "supplier": "Kliko", "lat": 53.00098157899074, "lng": 6.562365462635945}, {"id": 419, "number": "158bio", "street": "Kuyperstraat ", "type": "BIO", "subtype": "15L", "condition": "Goed", "color": "Antraciet", "supplier": "Kliko", "lat": 53.00188852315727, "lng": 6.562715810986668}, {"id": 420, "number": "159bio", "street": "Kuyperstraat ", "type": "BIO", "subtype": "15L", "condition": "Goed", "color": "Antraciet", "supplier": "Kliko", "lat": 53.001794817769095, "lng": 6.561955560473516}, {"id": 421, "number": "160bio", "street": "Kuyperstraat ", "type": "BIO", "subtype": "15L", "condition": "Goed", "color": "Antraciet", "supplier": "Kliko", "lat": 53.001690793775936, "lng": 6.561174602894735}, {"id": 422, "number": "161bio", "street": "Kuyperstraat ", "type": "BIO", "subtype": "15L", "condition": "Goed", "color": "Antraciet", "supplier": "Kliko", "lat": 53.00157608133288, "lng": 6.560341894270765}, {"id": 423, "number": "163bio", "street": "Troelstralaan ", "type": "BIO", "subtype": "15L", "condition": "Goed", "color": "Antraciet", "supplier": "Kliko", "lat": 53.00073402769159, "lng": 6.561104065381982}, {"id": 424, "number": "157bio", "street": "Sav. Lohmanstraat", "type": "BIO", "subtype": "15L", "condition": "Goed", "color": "Antraciet", "supplier": "Kliko", "lat": 53.000737478948494, "lng": 6.557742124922749}, {"id": 425, "number": "156bio", "street": "Schaperstraat", "type": "BIO", "subtype": "15L", "condition": "Goed", "color": "Antraciet", "supplier": "Kliko", "lat": 53.00107628572484, "lng": 6.556160498032913}, {"id": 426, "number": "165bio", "street": "Schaepmanstraat", "type": "BIO", "subtype": "15L", "condition": "Goed", "color": "Antraciet", "supplier": "Kliko", "lat": 52.99910620382613, "lng": 6.558153047571384}, {"id": 427, "number": "334bio", "street": "Bernardstraat", "type": "BIO", "subtype": "15L", "condition": "Goed", "color": "Antraciet", "supplier": "Kliko", "lat": 52.99890732691281, "lng": 6.560140876463008}, {"id": 428, "number": "167bio", "street": "Troelstralaan ", "type": "BIO", "subtype": "15L", "condition": "Goed", "color": "Antraciet", "supplier": "Kliko", "lat": 52.9987041802229, "lng": 6.554216147601035}, {"id": 429, "number": "168bio", "street": "Nansenstraat", "type": "BIO", "subtype": "15L", "condition": "Goed", "color": "Antraciet", "supplier": "Kliko", "lat": 52.99839930539492, "lng": 6.554509794291002}, {"id": 430, "number": null, "street": "Nansenstraat", "type": "Glas", "subtype": "Drie Kleuren", "condition": "Goed", "color": "Antraciet", "supplier": "Wastevision", "lat": 52.99841537644695, "lng": 6.5544971352320385}, {"id": 431, "number": "282bio", "street": "Troelstralaan ", "type": "BIO", "subtype": "15L", "condition": "Goed", "color": "Antraciet", "supplier": "Kliko", "lat": 52.99834170073961, "lng": 6.5535449470820195}, {"id": 432, "number": "280bio", "street": "Thorbeckelaan ", "type": "BIO", "subtype": "15L", "condition": "Goed", "color": "Antraciet", "supplier": "Kliko", "lat": 52.99979192640989, "lng": 6.551951752586258}, {"id": 433, "number": "311bio", "street": "Stadhouderslaan", "type": "BIO", "subtype": "15L", "condition": "Goed", "color": "Antraciet", "supplier": "Kliko", "lat": 53.00182157245482, "lng": 6.551959907492409}, {"id": 434, "number": "150bio", "street": "Echtenstraat", "type": "BIO", "subtype": "15L", "condition": "Goed", "color": "Antraciet", "supplier": "Kliko", "lat": 53.00369001628766, "lng": 6.555809195671405}, {"id": 435, "number": "149bio", "street": "Molenstraat", "type": "BIO", "subtype": "15L", "condition": "Goed", "color": "Antraciet", "supplier": "Kliko", "lat": 53.00388952039659, "lng": 6.55675291450492}, {"id": 436, "number": "151bio", "street": "Cort vd Lindenstraat", "type": "BIO", "subtype": "15L", "condition": "Goed", "color": "Antraciet", "supplier": "Kliko", "lat": 53.00325593904836, "lng": 6.55996075167211}, {"id": 437, "number": "238bio", "street": "Molenstraat ", "type": "BIO", "subtype": "15L", "condition": "Goed", "color": "Antraciet", "supplier": "Kliko", "lat": 53.006439451139464, "lng": 6.557951278772019}, {"id": 438, "number": "237bio", "street": "Zwartwatersweg", "type": "BIO", "subtype": "15L", "condition": "Goed", "color": "Antraciet", "supplier": "Kliko", "lat": 53.0065864077674, "lng": 6.559416361830156}, {"id": 439, "number": "142bio", "street": "Smetanalaan", "type": "BIO", "subtype": "15L", "condition": "Goed", "color": "Antraciet", "supplier": "Kliko", "lat": 53.010919793929, "lng": 6.566216472885344}, {"id": 440, "number": "143bio", "street": "Smetanalaan", "type": "BIO", "subtype": "15L", "condition": "Goed", "color": "Antraciet", "supplier": "Kliko", "lat": 53.01114449856593, "lng": 6.564873486145671}, {"id": 441, "number": "144bio", "street": "Smetanalaan ", "type": "BIO", "subtype": "15L", "condition": "Goed", "color": "Antraciet", "supplier": "Kliko", "lat": 53.01135489397589, "lng": 6.5635458507159266}, {"id": 442, "number": "304bio", "street": "Smetanalaan ", "type": "BIO", "subtype": "15L", "condition": "Goed", "color": "Antraciet", "supplier": "Kliko", "lat": 53.01169614630097, "lng": 6.562826634346621}, {"id": 444, "number": "709 ", "street": "Beunheugte", "type": "PMD", "subtype": "Trommel", "condition": "Goed", "color": "Antraciet", "supplier": "Vconsyst", "lat": 53.01737273663582, "lng": 6.583269005074196}, {"id": 445, "number": "103", "street": "Beunheugte", "type": "Papier", "subtype": "Trommel", "condition": "Goed", "color": "Antraciet", "supplier": "Vconsyst", "lat": 53.01738933184, "lng": 6.583248590859355}, {"id": 446, "number": "153", "street": "Thorbeckelaan", "type": "Papier", "subtype": "Trommel", "condition": "Goed", "color": "Antraciet", "supplier": "Vconsyst", "lat": 53.00043438466433, "lng": 6.552806178880553}, {"id": 447, "number": "753", "street": "Thorbeckelaan", "type": "PMD", "subtype": "Trommel", "condition": "Goed", "color": "Antraciet", "supplier": "Vconsyst", "lat": 53.00042165482001, "lng": 6.552773548476186}, {"id": 448, "number": "754", "street": "Thorbeckelaan ", "type": "PMD", "subtype": "60L", "condition": "Goed", "color": "Antraciet", "supplier": "Vconsyst", "lat": 53.00001681061945, "lng": 6.551624556515396}, {"id": 449, "number": "154", "street": "Thorbeckelaan ", "type": "Papier", "subtype": "Trommel", "condition": "Goed", "color": "Antraciet", "supplier": "Vconsyst", "lat": 52.99994111356209, "lng": 6.551455357933327}, {"id": 450, "number": "148 ", "street": "Klenckestraat", "type": "Papier", "subtype": "Trommel", "condition": "Goed", "color": "Antraciet", "supplier": "Vconsyst", "lat": 53.004574263730696, "lng": 6.5502011516931935}, {"id": 451, "number": "748", "street": "Klenckestraat ", "type": "PMD", "subtype": "Trommel", "condition": "Goed", "color": "Antraciet", "supplier": "Vconsyst", "lat": 53.00461575187152, "lng": 6.550107040590776}, {"id": 452, "number": "338", "street": "Beilerstraat ", "type": "Papier", "subtype": "Klep", "condition": "Goed", "color": "Antraciet", "supplier": "Vconsyst", "lat": 52.97808660607876, "lng": 6.557548727523536}, {"id": 453, "number": "338", "street": "Beilerstraat", "type": "Restafval", "subtype": "60L", "condition": "Goed", "color": "Antraciet", "supplier": "Vconsyst", "lat": 52.97802932050014, "lng": 6.55750199716246}, {"id": 454, "number": "337", "street": "Hendrik van boeijenlaan", "type": "Restafval", "subtype": "60L", "condition": "Goed", "color": "Antraciet", "supplier": "Vconsyst", "lat": 52.975035491204025, "lng": 6.56826577169522}, {"id": 455, "number": "737", "street": "Hendrik van boeijenlaan", "type": "PMD", "subtype": "60L", "condition": "Goed", "color": "Antraciet", "supplier": "Vconsyst", "lat": 52.975050621074296, "lng": 6.568288373307759}, {"id": 456, "number": "337", "street": "Hendrik van boeijenlaan ", "type": "Papier", "subtype": "60L", "condition": "Goed", "color": "Antraciet", "supplier": "Vconsyst", "lat": 52.97506749057587, "lng": 6.568307829918492}, {"id": 457, "number": "337", "street": "Hendrik van boeijenlaan ", "type": "BIO", "subtype": "15L", "condition": "Goed", "color": "Antraciet", "supplier": "Kliko", "lat": 52.97509014857909, "lng": 6.568329165804821}, {"id": 458, "number": "129", "street": "Anemoonstraat", "type": "Papier", "subtype": "Trommel", "condition": "Goed", "color": "Antraciet", "supplier": "Vconsyst", "lat": 52.987063908721616, "lng": 6.569708003409158}, {"id": 459, "number": "708", "street": "Anemoonstraat", "type": "PMD", "subtype": "Trommel", "condition": "Goed", "color": null, "supplier": null, "lat": 52.987044054461414, "lng": 6.569702069138366}, {"id": 460, "number": "127", "street": "Berkenstraat", "type": "Papier", "subtype": "Trommel", "condition": "Goed", "color": "Antraciet", "supplier": "Vconsyst", "lat": 52.985198901461494, "lng": 6.569758637848454}, {"id": 461, "number": "257", "street": "Stoepveldsingel", "type": "BIO", "subtype": "Trommel", "condition": "Goed", "color": "Antraciet", "supplier": "Kliko", "lat": 53.012456054075045, "lng": 6.590137376412863}, {"id": 462, "number": "255", "street": "Overstelpen", "type": "BIO", "subtype": "Trommel", "condition": "Goed", "color": "Antraciet", "supplier": "Kliko", "lat": 53.01310532763367, "lng": 6.588757640493263}, {"id": 463, "number": "903", "street": "Walakker", "type": "Glas", "subtype": null, "condition": "Redelijk", "color": "Antraciet", "supplier": "Engels", "lat": 53.016040364472296, "lng": 6.561092073771261}, {"id": 464, "number": "904", "street": "Walakker", "type": "Glas", "subtype": null, "condition": "Redelijk", "color": "Antraciet", "supplier": "Engels", "lat": 53.016038024999375, "lng": 6.561061192386742}, {"id": 465, "number": "931", "street": "Anemoonstraat", "type": "Glas", "subtype": null, "condition": "Goed", "color": "Antraciet", "supplier": "Vconsyst", "lat": 52.9869482786455, "lng": 6.569677267551701}, {"id": 466, "number": "935", "street": "Diepstroeten", "type": "Glas", "subtype": null, "condition": "Goed", "color": "Antraciet", "supplier": "Wastevision", "lat": 52.97044718698114, "lng": 6.569166387564774}, {"id": 467, "number": "936", "street": "Diepstroeten", "type": "Glas", "subtype": "Bruin/Groen", "condition": "Goed", "color": "Antraciet", "supplier": "Wastevision", "lat": 52.970418852641274, "lng": 6.569091588444323}, {"id": 468, "number": "937", "street": "Weierstraat", "type": "Glas", "subtype": "Wit", "condition": "Goed", "color": "Antraciet", "supplier": "Wastevision", "lat": 52.994839258844245, "lng": 6.5592777895110626}, {"id": 469, "number": "938", "street": "Weierstraat", "type": "Glas", "subtype": "Bruin/Groen", "condition": "Goed", "color": "Antraciet", "supplier": "Wastevision", "lat": 52.994835622201805, "lng": 6.559245165394873}, {"id": 470, "number": "941", "street": "M.L. Kingweg", "type": "Glas", "subtype": "Wit", "condition": "Goed", "color": "Antraciet", "supplier": "Wastevision", "lat": 53.01733077007092, "lng": 6.57272543905862}, {"id": 471, "number": "942", "street": "M.L Kingweg", "type": "Glas", "subtype": "Bruin/Groen", "condition": "Goed", "color": "Antraciet", "supplier": "Wastevision", "lat": 53.01731042336773, "lng": 6.572716323853438}]